[{"adId":17,"campaignId":8122,"keyWords":["lego+city+buildings+"],"relevanceScore":0.0,"pClick":0.0,"bidPrice":4.5,"rankScore":0.0,"qualityScore":0.0,"costPerClick":0.0,"position":0,"title":"LEGO Creator Corner Deli 31050","price":28.99,"thumbnail":"https://images-na.ssl-images-amazon.com/images/I/61Mxwi2R9ML._AC_US218_.jpg","description":null,"brand":"LEGO","detail_url":"https://www.amazon.com/dp/B017B1BESC","query":"lego city buildings ","query_group_id":0,"category":"Toys & Games"},{"adId":17,"campaignId":8122,"keyWords":["lego+city+buildings+"],"relevanceScore":0.0,"pClick":0.0,"bidPrice":4.5,"rankScore":0.0,"qualityScore":0.0,"costPerClick":0.0,"position":0,"title":"LEGO Creator Park Street Townhouse 31065 Building Kit","price":39.99,"thumbnail":"https://images-na.ssl-images-amazon.com/images/I/5143pSYfygL._AC_US218_.jpg","description":null,"brand":"LEGO","detail_url":"https://www.amazon.com/dp/B01KJEOBJ2","query":"lego city buildings ","query_group_id":0,"category":"Toys & Games"},{"adId":17,"campaignId":8122,"keyWords":["lego+city+buildings+"],"relevanceScore":0.0,"pClick":0.0,"bidPrice":4.5,"rankScore":0.0,"qualityScore":0.0,"costPerClick":0.0,"position":0,"title":"LEGO City Town 60097 City Square Building Kit","price":141.99,"thumbnail":"https://images-na.ssl-images-amazon.com/images/I/61QqqvKvjYL._AC_US218_.jpg","description":null,"brand":"LEGO","detail_url":"https://www.amazon.com/dp/B00WI0GEMS","query":"lego city buildings ","query_group_id":0,"category":"Toys & Games"},{"adId":17,"campaignId":8122,"keyWords":["lego+city+buildings+"],"relevanceScore":0.0,"pClick":0.0,"bidPrice":4.5,"rankScore":0.0,"qualityScore":0.0,"costPerClick":0.0,"position":0,"title":"","price":0.0,"thumbnail":"","description":null,"brand":"","detail_url":"https://www.amazon.com/dp/B005LRS9Y6","query":"lego city buildings ","query_group_id":0,"category":"Toys & Games"},{"adId":17,"campaignId":8122,"keyWords":["lego+city+buildings+"],"relevanceScore":0.0,"pClick":0.0,"bidPrice":4.5,"rankScore":0.0,"qualityScore":0.0,"costPerClick":0.0,"position":0,"title":"LEGO Architecture New York City 21028, Skyline Collection, Building Blocks","price":47.99,"thumbnail":"https://images-na.ssl-images-amazon.com/images/I/51JvqOf6-SL._AC_US218_.jpg","description":null,"brand":"LEGO","detail_url":"https://www.amazon.com/dp/B017B19DOY","query":"lego city buildings ","query_group_id":0,"category":"Toys & Games"},{"adId":17,"campaignId":8122,"keyWords":["lego+city+buildings+"],"relevanceScore":0.0,"pClick":0.0,"bidPrice":4.5,"rankScore":0.0,"qualityScore":0.0,"costPerClick":0.0,"position":0,"title":"LEGO Creator Expert Detective's Office","price":159.95,"thumbnail":"https://images-na.ssl-images-amazon.com/images/I/61qfkYRB-OL._AC_US218_.jpg","description":null,"brand":"LEGO","detail_url":"https://www.amazon.com/dp/B00NHQGDZ0","query":"lego city buildings ","query_group_id":0,"category":"Toys & Games"},{"adId":17,"campaignId":8122,"keyWords":["lego+city+buildings+"],"relevanceScore":0.0,"pClick":0.0,"bidPrice":4.5,"rankScore":0.0,"qualityScore":0.0,"costPerClick":0.0,"position":0,"title":"LEGO Creator Toy and Grocery Shop","price":64.75,"thumbnail":"https://images-na.ssl-images-amazon.com/images/I/615o4oJihgL._AC_US218_.jpg","description":null,"brand":"LEGO","detail_url":"https://www.amazon.com/dp/B00NHQGGNO","query":"lego city buildings ","query_group_id":0,"category":"Toys & Games"},{"adId":17,"campaignId":8122,"keyWords":["lego+city+buildings+"],"relevanceScore":0.0,"pClick":0.0,"bidPrice":4.5,"rankScore":0.0,"qualityScore":0.0,"costPerClick":0.0,"position":0,"title":"LEGO City Town 60134 Fun in the park - City People Pack Building Kit (157 Piece)","price":28.97,"thumbnail":"https://images-na.ssl-images-amazon.com/images/I/61kyn-CVGAL._AC_US218_.jpg","description":null,"brand":"LEGO","detail_url":"https://www.amazon.com/dp/B01CU9WX08","query":"lego city buildings ","query_group_id":0,"category":"Toys & Games"},{"adId":17,"campaignId":8122,"keyWords":["lego+city+buildings+"],"relevanceScore":0.0,"pClick":0.0,"bidPrice":4.5,"rankScore":0.0,"qualityScore":0.0,"costPerClick":0.0,"position":0,"title":"LEGO City Town 60132 Service Station Building Kit (515 Piece)","price":64.22,"thumbnail":"https://images-na.ssl-images-amazon.com/images/I/51hlqus3SsL._AC_US218_.jpg","description":null,"brand":"LEGO","detail_url":"https://www.amazon.com/dp/B01CU9WX1C","query":"lego city buildings ","query_group_id":0,"category":"Toys & Games"},{"adId":17,"campaignId":8122,"keyWords":["lego+city+buildings+"],"relevanceScore":0.0,"pClick":0.0,"bidPrice":4.5,"rankScore":0.0,"qualityScore":0.0,"costPerClick":0.0,"position":0,"title":"LEGO Creator Lakeside Lodge 31048","price":19.19,"thumbnail":"https://images-na.ssl-images-amazon.com/images/I/51E7Wco0eOL._AC_US218_.jpg","description":null,"brand":"LEGO","detail_url":"https://www.amazon.com/dp/B017B1BEBE","query":"lego city buildings ","query_group_id":0,"category":"Toys & Games"},{"adId":17,"campaignId":8122,"keyWords":["lego+city+buildings+"],"relevanceScore":0.0,"pClick":0.0,"bidPrice":4.5,"rankScore":0.0,"qualityScore":0.0,"costPerClick":0.0,"position":0,"title":"LEGO CITY Fire Station 60110","price":79.99,"thumbnail":"https://images-na.ssl-images-amazon.com/images/I/61YVvdrgY0L._AC_US218_.jpg","description":null,"brand":"LEGO","detail_url":"https://www.amazon.com/dp/B017B1ASVG","query":"lego city buildings ","query_group_id":0,"category":"Toys & Games"},{"adId":17,"campaignId":8122,"keyWords":["lego+city+buildings+"],"relevanceScore":0.0,"pClick":0.0,"bidPrice":4.5,"rankScore":0.0,"qualityScore":0.0,"costPerClick":0.0,"position":0,"title":"LEGO City ATV Race Team 60148 Best Toy","price":12.79,"thumbnail":"https://images-na.ssl-images-amazon.com/images/I/61WlmiKpLkL._AC_US218_.jpg","description":null,"brand":"LEGO","detail_url":"https://www.amazon.com/dp/B01KKTNB7O","query":"lego city buildings ","query_group_id":0,"category":"Toys & Games"},{"adId":17,"campaignId":8122,"keyWords":["lego+city+buildings+"],"relevanceScore":0.0,"pClick":0.0,"bidPrice":4.5,"rankScore":0.0,"qualityScore":0.0,"costPerClick":0.0,"position":0,"title":"LEGO City Trains Cargo Train 60052 Building Toy","price":199.95,"thumbnail":"https://images-na.ssl-images-amazon.com/images/I/61MapIfp7NL._AC_US218_.jpg","description":null,"brand":"LEGO","detail_url":"https://www.amazon.com/dp/B00J4S6UYO","query":"lego city buildings ","query_group_id":0,"category":"Toys & Games"},{"adId":17,"campaignId":8122,"keyWords":["lego+city+buildings+"],"relevanceScore":0.0,"pClick":0.0,"bidPrice":4.5,"rankScore":0.0,"qualityScore":0.0,"costPerClick":0.0,"position":0,"title":"LEGO City Police Police Station 60141 Building Kit","price":79.99,"thumbnail":"https://images-na.ssl-images-amazon.com/images/I/613zZ6266CL._AC_US218_.jpg","description":null,"brand":"LEGO","detail_url":"https://www.amazon.com/dp/B01KKTNA6Q","query":"lego city buildings ","query_group_id":0,"category":"Toys & Games"},{"adId":17,"campaignId":8122,"keyWords":["lego+city+buildings+"],"relevanceScore":0.0,"pClick":0.0,"bidPrice":4.5,"rankScore":0.0,"qualityScore":0.0,"costPerClick":0.0,"position":0,"title":"LEGO City Town T-Junction and Curve Plate 7281 Building Kit","price":14.6,"thumbnail":"https://images-na.ssl-images-amazon.com/images/I/51MBUsmpPYL._AC_US218_.jpg","description":null,"brand":"LEGO","detail_url":"https://www.amazon.com/dp/B007WSS1AO","query":"lego city buildings ","query_group_id":0,"category":"Toys & Games"},{"adId":17,"campaignId":8122,"keyWords":["lego+city+buildings+"],"relevanceScore":0.0,"pClick":0.0,"bidPrice":4.5,"rankScore":0.0,"qualityScore":0.0,"costPerClick":0.0,"position":0,"title":"The LEGO Neighborhood Book: Build Your Own Town!","price":14.19,"thumbnail":"https://images-na.ssl-images-amazon.com/images/I/61AEUHAPisL._AC_US218_.jpg","description":null,"brand":"","detail_url":"https://www.amazon.com/dp/1593275714","query":"lego city buildings ","query_group_id":0,"category":"Toys & Games"},{"adId":17,"campaignId":8122,"keyWords":["lego+city+buildings+"],"relevanceScore":0.0,"pClick":0.0,"bidPrice":4.5,"rankScore":0.0,"qualityScore":0.0,"costPerClick":0.0,"position":0,"title":"Peel-and-Stick Baseplates - Self Adhesive Brick Building Plates - Compatible With Most Major Brands of Building Bricks - 4 pack (10\" x 10\") - By Creative QT (4-Blue)","price":29.95,"thumbnail":"https://images-na.ssl-images-amazon.com/images/I/61d+jkr4QiL._AC_US218_.jpg","description":null,"brand":"Creative QT","detail_url":"https://www.amazon.com/dp/B01CO2NQ0M","query":"lego city buildings ","query_group_id":0,"category":"Toys & Games"},{"adId":17,"campaignId":8122,"keyWords":["lego+city+buildings+"],"relevanceScore":0.0,"pClick":0.0,"bidPrice":4.5,"rankScore":0.0,"qualityScore":0.0,"costPerClick":0.0,"position":0,"title":"LEGO Juniors Fire Patrol Suitcase 10740 Building Kit","price":15.99,"thumbnail":"https://images-na.ssl-images-amazon.com/images/I/51lQN0V3hpL._AC_US218_.jpg","description":null,"brand":"LEGO Juniors","detail_url":"https://www.amazon.com/dp/B01KJENV48","query":"lego city buildings ","query_group_id":0,"category":"Toys & Games"},{"adId":17,"campaignId":8122,"keyWords":["lego+city+buildings+"],"relevanceScore":0.0,"pClick":0.0,"bidPrice":4.5,"rankScore":0.0,"qualityScore":0.0,"costPerClick":0.0,"position":0,"title":"Laser Pegs 4-in-1 Aircraft Building Set","price":12.99,"thumbnail":"https://images-na.ssl-images-amazon.com/images/I/51DjEuuF9nL._AC_US218_.jpg","description":null,"brand":"Laser Pegs","detail_url":"https://www.amazon.com/dp/B00J4S5KJA","query":"lego city buildings ","query_group_id":0,"category":"Toys & Games"},{"adId":17,"campaignId":8122,"keyWords":["lego+city+buildings+"],"relevanceScore":0.0,"pClick":0.0,"bidPrice":4.5,"rankScore":0.0,"qualityScore":0.0,"costPerClick":0.0,"position":0,"title":"ECO Builder City series-Fire station building blocks #1065 for 12 month+ kids","price":28.99,"thumbnail":"https://images-na.ssl-images-amazon.com/images/I/51Ovb-OIqpL._AC_US218_.jpg","description":null,"brand":"KT Toy","detail_url":"https://www.amazon.com/dp/B06XJD2BV6","query":"lego city buildings ","query_group_id":0,"category":"Toys & Games"},{"adId":17,"campaignId":8122,"keyWords":["lego+city+buildings+"],"relevanceScore":0.0,"pClick":0.0,"bidPrice":4.5,"rankScore":0.0,"qualityScore":0.0,"costPerClick":0.0,"position":0,"title":"LEGO Creator 10232 Palace Cinema","price":149.95,"thumbnail":"https://images-na.ssl-images-amazon.com/images/I/615ghAFaqUL._AC_US218_.jpg","description":null,"brand":"LEGO","detail_url":"https://www.amazon.com/dp/B00BFXP3G2","query":"lego city buildings ","query_group_id":0,"category":"Toys & Games"},{"adId":17,"campaignId":8122,"keyWords":["lego+city+buildings+"],"relevanceScore":0.0,"pClick":0.0,"bidPrice":4.5,"rankScore":0.0,"qualityScore":0.0,"costPerClick":0.0,"position":0,"title":"LEGO City Trains High-speed Passenger Train 60051 Building Toy","price":149.95,"thumbnail":"https://images-na.ssl-images-amazon.com/images/I/61AWQ3RYw7L._AC_US218_.jpg","description":null,"brand":"LEGO","detail_url":"https://www.amazon.com/dp/B00J4S6PGC","query":"lego city buildings ","query_group_id":0,"category":"Toys & Games"},{"adId":17,"campaignId":8122,"keyWords":["lego+city+buildings+"],"relevanceScore":0.0,"pClick":0.0,"bidPrice":4.5,"rankScore":0.0,"qualityScore":0.0,"costPerClick":0.0,"position":0,"title":"LEGO City Police ATV Arrest 60135 Building Kit","price":5.49,"thumbnail":"https://images-na.ssl-images-amazon.com/images/I/51Yr594LX+L._AC_US218_.jpg","description":null,"brand":"LEGO","detail_url":"https://www.amazon.com/dp/B01KKTN9F8","query":"lego city buildings ","query_group_id":0,"category":"Toys & Games"},{"adId":17,"campaignId":8122,"keyWords":["lego+city+buildings+"],"relevanceScore":0.0,"pClick":0.0,"bidPrice":4.5,"rankScore":0.0,"qualityScore":0.0,"costPerClick":0.0,"position":0,"title":"LEGO CITY Ferry 60119","price":21.99,"thumbnail":"https://images-na.ssl-images-amazon.com/images/I/51XrRxsdzEL._AC_US218_.jpg","description":null,"brand":"LEGO","detail_url":"https://www.amazon.com/dp/B017B1B2W0","query":"lego city buildings ","query_group_id":0,"category":"Toys & Games"},{"adId":17,"campaignId":8122,"keyWords":["lego+city+buildings+"],"relevanceScore":0.0,"pClick":0.0,"bidPrice":4.5,"rankScore":0.0,"qualityScore":0.0,"costPerClick":0.0,"position":0,"title":"10 Pieces Lego Compatible Minifigures Men People City Building Bricks Blocks Mini Figures Minifigs Minifigures Set Pack Collection Early Learning DevelopmentToys","price":9.47,"thumbnail":"https://images-na.ssl-images-amazon.com/images/I/51O4sRjHvYL._AC_US218_.jpg","description":null,"brand":"World Minifigures","detail_url":"https://www.amazon.com/dp/B01JXCZ9FQ","query":"lego city buildings ","query_group_id":0,"category":"Toys & Games"},{"adId":17,"campaignId":8122,"keyWords":["lego+city+buildings+"],"relevanceScore":0.0,"pClick":0.0,"bidPrice":4.5,"rankScore":0.0,"qualityScore":0.0,"costPerClick":0.0,"position":0,"title":"LEGO City Great Vehicles 4x4 with Catamaran 60149 Building Kit","price":15.59,"thumbnail":"https://images-na.ssl-images-amazon.com/images/I/61UZIsGc9kL._AC_US218_.jpg","description":null,"brand":"LEGO","detail_url":"https://www.amazon.com/dp/B01KKTNB5G","query":"lego city buildings ","query_group_id":0,"category":"Toys & Games"},{"adId":17,"campaignId":8122,"keyWords":["lego+city+buildings+"],"relevanceScore":0.0,"pClick":0.0,"bidPrice":4.5,"rankScore":0.0,"qualityScore":0.0,"costPerClick":0.0,"position":0,"title":"LEGO City Cargo Train 7939 (Discontinued by manufacturer)","price":0.0,"thumbnail":"https://images-na.ssl-images-amazon.com/images/I/51Tpn67eS9L._AC_US218_.jpg","description":null,"brand":"LEGO","detail_url":"https://www.amazon.com/dp/B003A2JCR2","query":"lego city buildings ","query_group_id":0,"category":"Toys & Games"},{"adId":17,"campaignId":8122,"keyWords":["lego+city+buildings+"],"relevanceScore":0.0,"pClick":0.0,"bidPrice":4.5,"rankScore":0.0,"qualityScore":0.0,"costPerClick":0.0,"position":0,"title":"LEGO City Airport 60104 Airport Passenger Terminal Building Kit (694 Piece)","price":75.99,"thumbnail":"https://images-na.ssl-images-amazon.com/images/I/616xEomDBuL._AC_US218_.jpg","description":null,"brand":"LEGO","detail_url":"https://www.amazon.com/dp/B01CU9WX3U","query":"lego city buildings ","query_group_id":0,"category":"Toys & Games"},{"adId":17,"campaignId":8122,"keyWords":["lego+city+buildings+"],"relevanceScore":0.0,"pClick":0.0,"bidPrice":4.5,"rankScore":0.0,"qualityScore":0.0,"costPerClick":0.0,"position":0,"title":"LEGO 60100 City Airport Starter Set, Building Kit (81 Piece)","price":7.99,"thumbnail":"https://images-na.ssl-images-amazon.com/images/I/61-cCsKgbXL._AC_US218_.jpg","description":null,"brand":"LEGO","detail_url":"https://www.amazon.com/dp/B01CU9WV50","query":"lego city buildings ","query_group_id":0,"category":"Toys & Games"},{"adId":17,"campaignId":8122,"keyWords":["lego+city+buildings+"],"relevanceScore":0.0,"pClick":0.0,"bidPrice":4.5,"rankScore":0.0,"qualityScore":0.0,"costPerClick":0.0,"position":0,"title":"LEGO City Police Mobile Command Center 60139 Building Kit","price":41.99,"thumbnail":"https://images-na.ssl-images-amazon.com/images/I/61U2ZWcyCXL._AC_US218_.jpg","description":null,"brand":"LEGO","detail_url":"https://www.amazon.com/dp/B01KKTN9J4","query":"lego city buildings ","query_group_id":0,"category":"Toys & Games"},{"adId":17,"campaignId":8122,"keyWords":["lego+city+buildings+"],"relevanceScore":0.0,"pClick":0.0,"bidPrice":4.5,"rankScore":0.0,"qualityScore":0.0,"costPerClick":0.0,"position":0,"title":"LEGO 2011 City Advent Calendar 7553","price":54.99,"thumbnail":"https://images-na.ssl-images-amazon.com/images/I/51hcPjozU9L._AC_US218_.jpg","description":null,"brand":"LEGO","detail_url":"https://www.amazon.com/dp/B004XONSLC","query":"lego city buildings ","query_group_id":0,"category":"Toys & Games"},{"adId":17,"campaignId":8122,"keyWords":["lego+city+buildings+"],"relevanceScore":0.0,"pClick":0.0,"bidPrice":4.5,"rankScore":0.0,"qualityScore":0.0,"costPerClick":0.0,"position":0,"title":"Power City Construction Super Skyscraper Building Kit","price":38.78,"thumbnail":"https://images-na.ssl-images-amazon.com/images/I/41f1SdVLbYL._AC_US218_.jpg","description":null,"brand":"POWER CITY CONSTRUCTION","detail_url":"https://www.amazon.com/dp/B00FFZO4IY","query":"lego city buildings ","query_group_id":0,"category":"Toys & Games"},{"adId":17,"campaignId":8122,"keyWords":["lego+city+buildings+"],"relevanceScore":0.0,"pClick":0.0,"bidPrice":4.5,"rankScore":0.0,"qualityScore":0.0,"costPerClick":0.0,"position":0,"title":"LEGO BATMAN MOVIE Mr. Freeze Ice Attack 70901 Building Kit (201 Piece)","price":15.99,"thumbnail":"https://images-na.ssl-images-amazon.com/images/I/51tZb1iKZuL._AC_US218_.jpg","description":null,"brand":"LEGO","detail_url":"https://www.amazon.com/dp/B01J8PBJYI","query":"lego city buildings ","query_group_id":0,"category":"Toys & Games"},{"adId":17,"campaignId":8122,"keyWords":["lego+city+buildings+"],"relevanceScore":0.0,"pClick":0.0,"bidPrice":4.5,"rankScore":0.0,"qualityScore":0.0,"costPerClick":0.0,"position":0,"title":"LEGO 10218 Creator Pet Shop","price":234.0,"thumbnail":"https://images-na.ssl-images-amazon.com/images/I/51mLWTVgX9L._AC_US218_.jpg","description":null,"brand":"Lego Creator","detail_url":"https://www.amazon.com/dp/B004P2HMNM","query":"lego city buildings ","query_group_id":0,"category":"Toys & Games"},{"adId":17,"campaignId":8122,"keyWords":["lego+city+buildings+"],"relevanceScore":0.0,"pClick":0.0,"bidPrice":4.5,"rankScore":0.0,"qualityScore":0.0,"costPerClick":0.0,"position":0,"title":"LEGO City Police Bulldozer Break-In 60140 Building Kit","price":55.99,"thumbnail":"https://images-na.ssl-images-amazon.com/images/I/51G7E9GgUfL._AC_US218_.jpg","description":null,"brand":"LEGO","detail_url":"https://www.amazon.com/dp/B01KKVPCC4","query":"lego city buildings ","query_group_id":0,"category":"Toys & Games"},{"adId":17,"campaignId":8122,"keyWords":["lego+city+buildings+"],"relevanceScore":0.0,"pClick":0.0,"bidPrice":4.5,"rankScore":0.0,"qualityScore":0.0,"costPerClick":0.0,"position":0,"title":"LEGO City Great Vehicles Sweeper & Excavator 60152 Building Toy","price":23.97,"thumbnail":"https://images-na.ssl-images-amazon.com/images/I/51xQBuhsIaL._AC_US218_.jpg","description":null,"brand":"LEGO","detail_url":"https://www.amazon.com/dp/B01KKTNBAG","query":"lego city buildings ","query_group_id":0,"category":"Toys & Games"},{"adId":17,"campaignId":8122,"keyWords":["lego+city+buildings+"],"relevanceScore":0.0,"pClick":0.0,"bidPrice":4.5,"rankScore":0.0,"qualityScore":0.0,"costPerClick":0.0,"position":0,"title":"YouCute Micro Blocks,Big Ben,Small Building Block Set","price":9.99,"thumbnail":"https://images-na.ssl-images-amazon.com/images/I/41jbnvZxADL._AC_US218_.jpg","description":null,"brand":"YouCute","detail_url":"https://www.amazon.com/dp/B01K1W0WH2","query":"lego city buildings ","query_group_id":0,"category":"Toys & Games"},{"adId":17,"campaignId":8122,"keyWords":["lego+city+buildings+"],"relevanceScore":0.0,"pClick":0.0,"bidPrice":4.5,"rankScore":0.0,"qualityScore":0.0,"costPerClick":0.0,"position":0,"title":"LEGO City Fire Emergency 60003","price":53.99,"thumbnail":"https://images-na.ssl-images-amazon.com/images/I/51qaD+HhG7L._AC_US218_.jpg","description":null,"brand":"LEGO","detail_url":"https://www.amazon.com/dp/B00A850SGS","query":"lego city buildings ","query_group_id":0,"category":"Toys & Games"},{"adId":17,"campaignId":8122,"keyWords":["lego+city+buildings+"],"relevanceScore":0.0,"pClick":0.0,"bidPrice":4.5,"rankScore":0.0,"qualityScore":0.0,"costPerClick":0.0,"position":0,"title":"LEGO CITY Fire Starter Set 60106","price":6.39,"thumbnail":"https://images-na.ssl-images-amazon.com/images/I/61gUT3fRb2L._AC_US218_.jpg","description":null,"brand":"LEGO","detail_url":"https://www.amazon.com/dp/B017B1ALMC","query":"lego city buildings ","query_group_id":0,"category":"Toys & Games"},{"adId":17,"campaignId":8122,"keyWords":["lego+city+buildings+"],"relevanceScore":0.0,"pClick":0.0,"bidPrice":4.5,"rankScore":0.0,"qualityScore":0.0,"costPerClick":0.0,"position":0,"title":"LEGO Atlantis Guardian of the Deep (8058)","price":49.99,"thumbnail":"https://images-na.ssl-images-amazon.com/images/I/51Y8QG9bM9L._AC_US218_.jpg","description":null,"brand":"LEGO","detail_url":"https://www.amazon.com/dp/B002RL7WEM","query":"lego city buildings ","query_group_id":0,"category":"Toys & Games"},{"adId":17,"campaignId":8122,"keyWords":["lego+city+buildings+"],"relevanceScore":0.0,"pClick":0.0,"bidPrice":4.5,"rankScore":0.0,"qualityScore":0.0,"costPerClick":0.0,"position":0,"title":"LEGO City Police Officer Key Chain 853568","price":5.99,"thumbnail":"https://images-na.ssl-images-amazon.com/images/I/4145lDcHxVL._AC_US218_.jpg","description":null,"brand":"LEGO","detail_url":"https://www.amazon.com/dp/B019VP2OE4","query":"lego city buildings ","query_group_id":0,"category":"Toys & Games"},{"adId":17,"campaignId":8122,"keyWords":["lego+city+buildings+"],"relevanceScore":0.0,"pClick":0.0,"bidPrice":4.5,"rankScore":0.0,"qualityScore":0.0,"costPerClick":0.0,"position":0,"title":"LEGO City Great Vehicles Buggy 60145 Building Kit","price":7.97,"thumbnail":"https://images-na.ssl-images-amazon.com/images/I/61MOZFzkMrL._AC_US218_.jpg","description":null,"brand":"LEGO","detail_url":"https://www.amazon.com/dp/B01KKTNB9W","query":"lego city buildings ","query_group_id":0,"category":"Toys & Games"},{"adId":17,"campaignId":8122,"keyWords":["lego+city+buildings+"],"relevanceScore":0.0,"pClick":0.0,"bidPrice":4.5,"rankScore":0.0,"qualityScore":0.0,"costPerClick":0.0,"position":0,"title":"LEGO Batman - PlayStation 2","price":21.74,"thumbnail":"https://images-na.ssl-images-amazon.com/images/I/51SQV8aoW7L._AC_US218_.jpg","description":"... them, while building and using ... all in their quirky LEGO form ...","brand":"","detail_url":"https://www.amazon.com/dp/B0015Z1I4G","query":"lego city buildings ","query_group_id":0,"category":"Toys & Games"},{"adId":17,"campaignId":8122,"keyWords":["lego+city+buildings+"],"relevanceScore":0.0,"pClick":0.0,"bidPrice":4.5,"rankScore":0.0,"qualityScore":0.0,"costPerClick":0.0,"position":0,"title":"LEGO Town Plan","price":0.0,"thumbnail":"https://images-na.ssl-images-amazon.com/images/I/51Yc1zujHvL._AC_US218_.jpg","description":null,"brand":"LEGO","detail_url":"https://www.amazon.com/dp/B000WLW3WU","query":"lego city buildings ","query_group_id":0,"category":"Toys & Games"},{"adId":17,"campaignId":8122,"keyWords":["lego+city+buildings+"],"relevanceScore":0.0,"pClick":0.0,"bidPrice":4.5,"rankScore":0.0,"qualityScore":0.0,"costPerClick":0.0,"position":0,"title":"PARTY PACK SPECIAL - Lego Inspired Happy Birthday Collection - YellowRed Blue Green Building Block background","price":49.0,"thumbnail":"https://images-na.ssl-images-amazon.com/images/I/61nBBGvV+xL._AC_US218_.jpg","description":null,"brand":"Emerald City Paperie","detail_url":"https://www.amazon.com/dp/B01BZJ5V3A","query":"lego city buildings ","query_group_id":0,"category":"Toys & Games"},{"adId":17,"campaignId":8122,"keyWords":["lego+city+buildings+"],"relevanceScore":0.0,"pClick":0.0,"bidPrice":4.5,"rankScore":0.0,"qualityScore":0.0,"costPerClick":0.0,"position":0,"title":"Black Widow mini figure building blocks compatible figure from 76032 The Avengers Quinjet City Chase","price":24.99,"thumbnail":"https://images-na.ssl-images-amazon.com/images/I/318MX6+lH6L._AC_US218_.jpg","description":null,"brand":"","detail_url":"https://www.amazon.com/dp/B01MEEUTZU","query":"lego city buildings ","query_group_id":0,"category":"Toys & Games"},{"adId":17,"campaignId":8122,"keyWords":["lego+city+buildings+"],"relevanceScore":0.0,"pClick":0.0,"bidPrice":4.5,"rankScore":0.0,"qualityScore":0.0,"costPerClick":0.0,"position":0,"title":"LEGO Creator Expert Brick Bank Building Kit (2380 Piece)","price":169.95,"thumbnail":"https://images-na.ssl-images-amazon.com/images/I/6159TeEJGtL._AC_US218_.jpg","description":null,"brand":"LEGO","detail_url":"https://www.amazon.com/dp/B01A85FXBC","query":"lego city buildings ","query_group_id":0,"category":"Toys & Games"},{"adId":17,"campaignId":8122,"keyWords":["lego+city+buildings+"],"relevanceScore":0.0,"pClick":0.0,"bidPrice":4.5,"rankScore":0.0,"qualityScore":0.0,"costPerClick":0.0,"position":0,"title":"LEGO City: Build Your Own Adventure","price":15.61,"thumbnail":"https://images-na.ssl-images-amazon.com/images/I/61jIt7RsoCL._AC_US218_.jpg","description":null,"brand":"","detail_url":"https://www.amazon.com/dp/1465450467","query":"lego city buildings ","query_group_id":0,"category":"Toys & Games"},{"adId":17,"campaignId":8122,"keyWords":["lego+city+buildings+"],"relevanceScore":0.0,"pClick":0.0,"bidPrice":4.5,"rankScore":0.0,"qualityScore":0.0,"costPerClick":0.0,"position":0,"title":"Rat-A-Tat","price":11.489999999999998,"thumbnail":"https://images-na.ssl-images-amazon.com/images/I/51MwGsR8tDL._PI_PJStripe-Prime-Only-500px,TopLeft,0,0_AC_US218_.jpg","description":null,"brand":"","detail_url":"https://www.amazon.com/dp/B01M2WM9ZR","query":"lego city buildings ","query_group_id":0,"category":"Toys & Games"}]