[{"adId":15,"campaignId":8101,"keyWords":["all+weather+outdoor+furniture+"],"relevanceScore":0.0,"pClick":0.0,"bidPrice":17.0,"rankScore":0.0,"qualityScore":0.0,"costPerClick":0.0,"position":0,"title":"Keter Rio 3 Pc All Weather Outdoor Patio Garden Conversation Chair & Table Set Furniture, Brown","price":89.53,"thumbnail":"https://images-na.ssl-images-amazon.com/images/I/41DoQTKNwJL._AC_US218_.jpg","description":null,"brand":"Keter","detail_url":"https://www.amazon.com/dp/B00K8945QS","query":"all weather outdoor furniture ","query_group_id":0,"category":"Patio, Lawn & Garden"},{"adId":15,"campaignId":8101,"keyWords":["all+weather+outdoor+furniture+"],"relevanceScore":0.0,"pClick":0.0,"bidPrice":17.0,"rankScore":0.0,"qualityScore":0.0,"costPerClick":0.0,"position":0,"title":"Keter Corfu 4 Piece Set All Weather Outdoor Patio Garden Furniture w/ Cushions, Brown","price":307.6,"thumbnail":"https://images-na.ssl-images-amazon.com/images/I/41ycYfo+cuL._AC_US218_.jpg","description":null,"brand":"Keter","detail_url":"https://www.amazon.com/dp/B007MJFI0Y","query":"all weather outdoor furniture ","query_group_id":0,"category":"Patio, Lawn & Garden"},{"adId":15,"campaignId":8101,"keyWords":["all+weather+outdoor+furniture+"],"relevanceScore":0.0,"pClick":0.0,"bidPrice":17.0,"rankScore":0.0,"qualityScore":0.0,"costPerClick":0.0,"position":0,"title":"Best ChoiceProducts Wicker Adirondack Chair Patio Porch Deck Furniture Outdoor All Weather Proof","price":99.94,"thumbnail":"https://images-na.ssl-images-amazon.com/images/I/51-Mps3R3QL._AC_US218_.jpg","description":null,"brand":"BestChoiceproducts","detail_url":"https://www.amazon.com/dp/B00Y3RD1YS","query":"all weather outdoor furniture ","query_group_id":0,"category":"Patio, Lawn & Garden"},{"adId":15,"campaignId":8101,"keyWords":["all+weather+outdoor+furniture+"],"relevanceScore":0.0,"pClick":0.0,"bidPrice":17.0,"rankScore":0.0,"qualityScore":0.0,"costPerClick":0.0,"position":0,"title":"Keter Corfu Armchair All Weather Outdoor Patio Garden Furniture with Cushions, Charcoal","price":61.44,"thumbnail":"https://images-na.ssl-images-amazon.com/images/I/514VwpP1UbL._AC_US218_.jpg","description":null,"brand":"Keter","detail_url":"https://www.amazon.com/dp/B00C5C7OS2","query":"all weather outdoor furniture ","query_group_id":0,"category":"Patio, Lawn & Garden"},{"adId":15,"campaignId":8101,"keyWords":["all+weather+outdoor+furniture+"],"relevanceScore":0.0,"pClick":0.0,"bidPrice":17.0,"rankScore":0.0,"qualityScore":0.0,"costPerClick":0.0,"position":0,"title":"Keter Eden 70 Gallon All Weather Outdoor Patio Storage Garden Bench Deck Box, Brown/Brown","price":155.87,"thumbnail":"https://images-na.ssl-images-amazon.com/images/I/41fM-aRTJkL._AC_US218_.jpg","description":null,"brand":"Keter","detail_url":"https://www.amazon.com/dp/B00E0JO5MG","query":"all weather outdoor furniture ","query_group_id":0,"category":"Patio, Lawn & Garden"},{"adId":15,"campaignId":8101,"keyWords":["all+weather+outdoor+furniture+"],"relevanceScore":0.0,"pClick":0.0,"bidPrice":17.0,"rankScore":0.0,"qualityScore":0.0,"costPerClick":0.0,"position":0,"title":"Merax 4 PCS Patio Rattan Furniture Set Cushioned Outdoor Garden Wicker Rattan furniture with Beige Cushion (Brown-NO.2)","price":169.99,"thumbnail":"https://images-na.ssl-images-amazon.com/images/I/61mq0OyCBkL._AC_US218_.jpg","description":null,"brand":"Merax","detail_url":"https://www.amazon.com/dp/B01GPYVKZI","query":"all weather outdoor furniture ","query_group_id":0,"category":"Patio, Lawn & Garden"},{"adId":15,"campaignId":8101,"keyWords":["all+weather+outdoor+furniture+"],"relevanceScore":0.0,"pClick":0.0,"bidPrice":17.0,"rankScore":0.0,"qualityScore":0.0,"costPerClick":0.0,"position":0,"title":"Greendale Home Fashions 17 x 17-Inch Toss Pillows, set of 2","price":10.16,"thumbnail":"https://images-na.ssl-images-amazon.com/images/I/51mqWCjXfRL._AC_US218_.jpg","description":null,"brand":"Greendale Home Fashions","detail_url":"https://www.amazon.com/dp/B007CW0KHW","query":"all weather outdoor furniture ","query_group_id":0,"category":"Patio, Lawn & Garden"},{"adId":15,"campaignId":8101,"keyWords":["all+weather+outdoor+furniture+"],"relevanceScore":0.0,"pClick":0.0,"bidPrice":17.0,"rankScore":0.0,"qualityScore":0.0,"costPerClick":0.0,"position":0,"title":"Modern Outdoor Garden, Patio 4 Piece Set - Wicker Sofa Furniture Set (Black / Ivory)","price":219.99,"thumbnail":"https://images-na.ssl-images-amazon.com/images/I/313CoSnI7dL._AC_US218_.jpg","description":null,"brand":"Divano Roma Furniture","detail_url":"https://www.amazon.com/dp/B01N100QM2","query":"all weather outdoor furniture ","query_group_id":0,"category":"Patio, Lawn & Garden"},{"adId":15,"campaignId":8101,"keyWords":["all+weather+outdoor+furniture+"],"relevanceScore":0.0,"pClick":0.0,"bidPrice":17.0,"rankScore":0.0,"qualityScore":0.0,"costPerClick":0.0,"position":0,"title":"Suncrown Outdoor Furniture Wicker Love-seat with Coffee Table (2-Piece Set) Built-In Storage Bin | Comfortable, All-Weather Cushions | Patio, Backyard, Porch, Garden, Poolside","price":219.95,"thumbnail":"https://images-na.ssl-images-amazon.com/images/I/61wjdMtkolL._AC_US218_.jpg","description":null,"brand":"Suncrown","detail_url":"https://www.amazon.com/dp/B06XFBH75H","query":"all weather outdoor furniture ","query_group_id":0,"category":"Patio, Lawn & Garden"},{"adId":15,"campaignId":8101,"keyWords":["all+weather+outdoor+furniture+"],"relevanceScore":0.0,"pClick":0.0,"bidPrice":17.0,"rankScore":0.0,"qualityScore":0.0,"costPerClick":0.0,"position":0,"title":"Patio Watcher Patio Chair Cover All Weather Protective Patio Furniture Cover High Back Outdoor Chair Cover(Grey)","price":18.99,"thumbnail":"https://images-na.ssl-images-amazon.com/images/I/41R63tI1rWL._AC_US218_.jpg","description":null,"brand":"Patio Watcher","detail_url":"https://www.amazon.com/dp/B01IOVYDSQ","query":"all weather outdoor furniture ","query_group_id":0,"category":"Patio, Lawn & Garden"},{"adId":15,"campaignId":8101,"keyWords":["all+weather+outdoor+furniture+"],"relevanceScore":0.0,"pClick":0.0,"bidPrice":17.0,"rankScore":0.0,"qualityScore":0.0,"costPerClick":0.0,"position":0,"title":"PATIOROMA 5pc Outdoor PE Wicker Rattan Sectional Furniture Set with Cream White Seat and Back Cushions, Red Throw Pillows, Steel Frame, Gray","price":379.99,"thumbnail":"https://images-na.ssl-images-amazon.com/images/I/51midgrg01L._AC_US218_.jpg","description":null,"brand":"PATIOROMA","detail_url":"https://www.amazon.com/dp/B06XHRFR4N","query":"all weather outdoor furniture ","query_group_id":0,"category":"Patio, Lawn & Garden"},{"adId":15,"campaignId":8101,"keyWords":["all+weather+outdoor+furniture+"],"relevanceScore":0.0,"pClick":0.0,"bidPrice":17.0,"rankScore":0.0,"qualityScore":0.0,"costPerClick":0.0,"position":0,"title":"Hopkins 90110ONLMI 2x4basics Flip Top BenchTable, Sand","price":56.7,"thumbnail":"https://images-na.ssl-images-amazon.com/images/I/41pHboL-21L._AC_US218_.jpg","description":null,"brand":"2x4 Basics","detail_url":"https://www.amazon.com/dp/B0015XGCN0","query":"all weather outdoor furniture ","query_group_id":0,"category":"Patio, Lawn & Garden"},{"adId":15,"campaignId":8101,"keyWords":["all+weather+outdoor+furniture+"],"relevanceScore":0.0,"pClick":0.0,"bidPrice":17.0,"rankScore":0.0,"qualityScore":0.0,"costPerClick":0.0,"position":0,"title":"Patio Watcher Patio Loveseat/Sofa Cover All Weather Protective Patio Furniture Sofa Cover with Secure Buckle Straps 76 Inches(Beige)","price":31.99,"thumbnail":"https://images-na.ssl-images-amazon.com/images/I/31jIRFzGmBL._AC_US218_.jpg","description":null,"brand":"Patio Watcher","detail_url":"https://www.amazon.com/dp/B06XSF7JW6","query":"all weather outdoor furniture ","query_group_id":0,"category":"Patio, Lawn & Garden"},{"adId":15,"campaignId":8101,"keyWords":["all+weather+outdoor+furniture+"],"relevanceScore":0.0,"pClick":0.0,"bidPrice":17.0,"rankScore":0.0,"qualityScore":0.0,"costPerClick":0.0,"position":0,"title":"Keter Pacific 2-Pack All-weather Adjustable Outdoor Patio Chaise Lounge Furniture, Graphite","price":281.1,"thumbnail":"https://images-na.ssl-images-amazon.com/images/I/31aqPV6hLyL._AC_US218_.jpg","description":null,"brand":"Keter","detail_url":"https://www.amazon.com/dp/B00C5C7OZA","query":"all weather outdoor furniture ","query_group_id":0,"category":"Patio, Lawn & Garden"},{"adId":15,"campaignId":8101,"keyWords":["all+weather+outdoor+furniture+"],"relevanceScore":0.0,"pClick":0.0,"bidPrice":17.0,"rankScore":0.0,"qualityScore":0.0,"costPerClick":0.0,"position":0,"title":"Merax 4 PC Outdoor Garden Rattan Patio Furniture Set Cushioned Seat Wicker Sofa (Brown)","price":134.9,"thumbnail":"https://images-na.ssl-images-amazon.com/images/I/41lNo89qZzL._AC_US218_.jpg","description":null,"brand":"Merax","detail_url":"https://www.amazon.com/dp/B01LWL2UY5","query":"all weather outdoor furniture ","query_group_id":0,"category":"Patio, Lawn & Garden"},{"adId":15,"campaignId":8101,"keyWords":["all+weather+outdoor+furniture+"],"relevanceScore":0.0,"pClick":0.0,"bidPrice":17.0,"rankScore":0.0,"qualityScore":0.0,"costPerClick":0.0,"position":0,"title":"Classic Accessories Terrazzo Stackable Patio Chair Cover - All Weather Protection Outdoor Furniture Cover (58972)","price":19.99,"thumbnail":"https://images-na.ssl-images-amazon.com/images/I/310tg4Fw01L._AC_US218_.jpg","description":null,"brand":"Classic Accessories","detail_url":"https://www.amazon.com/dp/B000MUBV1U","query":"all weather outdoor furniture ","query_group_id":0,"category":"Patio, Lawn & Garden"},{"adId":15,"campaignId":8101,"keyWords":["all+weather+outdoor+furniture+"],"relevanceScore":0.0,"pClick":0.0,"bidPrice":17.0,"rankScore":0.0,"qualityScore":0.0,"costPerClick":0.0,"position":0,"title":"Best Choice Products Wicker Ice Bucket Outdoor Patio Furniture All-Weather Beverage Cooler with Tray","price":84.94,"thumbnail":"https://images-na.ssl-images-amazon.com/images/I/51cj-AcL4SL._AC_US218_.jpg","description":null,"brand":"Best Choice Products","detail_url":"https://www.amazon.com/dp/B014I8PWMK","query":"all weather outdoor furniture ","query_group_id":0,"category":"Patio, Lawn & Garden"},{"adId":15,"campaignId":8101,"keyWords":["all+weather+outdoor+furniture+"],"relevanceScore":0.0,"pClick":0.0,"bidPrice":17.0,"rankScore":0.0,"qualityScore":0.0,"costPerClick":0.0,"position":0,"title":"Classic Accessories Terrazzo Round Patio Table Cover - All Weather Protection Outdoor Furniture Cover (58202-EC)","price":19.5,"thumbnail":"https://images-na.ssl-images-amazon.com/images/I/310dtiXfEHL._AC_US218_.jpg","description":null,"brand":"Classic Accessories","detail_url":"https://www.amazon.com/dp/B00BBAPA0S","query":"all weather outdoor furniture ","query_group_id":0,"category":"Patio, Lawn & Garden"},{"adId":15,"campaignId":8101,"keyWords":["all+weather+outdoor+furniture+"],"relevanceScore":0.0,"pClick":0.0,"bidPrice":17.0,"rankScore":0.0,"qualityScore":0.0,"costPerClick":0.0,"position":0,"title":"Patio Rectangular Table and Chair Set Cover, Waterproof, Outdoor All Weather Protection, Beige Color (Small)","price":29.49,"thumbnail":"https://images-na.ssl-images-amazon.com/images/I/31d3HGpG06L._AC_US218_.jpg","description":null,"brand":"uFurniture Cover","detail_url":"https://www.amazon.com/dp/B01AP47WZQ","query":"all weather outdoor furniture ","query_group_id":0,"category":"Patio, Lawn & Garden"},{"adId":15,"campaignId":8101,"keyWords":["all+weather+outdoor+furniture+"],"relevanceScore":0.0,"pClick":0.0,"bidPrice":17.0,"rankScore":0.0,"qualityScore":0.0,"costPerClick":0.0,"position":0,"title":"Patio Furniture Rocking Chair Brown Wicker Outdoor Porch All-Weather UV Treated","price":129.56,"thumbnail":"https://images-na.ssl-images-amazon.com/images/I/51Y+u4OdpSL._AC_US218_.jpg","description":"All-weather wicker rocker Chair supports up to 250 lbs Gentle rocking action","brand":"Azalea Ridge","detail_url":"https://www.amazon.com/dp/B01A9QZLYO","query":"all weather outdoor furniture ","query_group_id":0,"category":"Patio, Lawn & Garden"},{"adId":15,"campaignId":8101,"keyWords":["all+weather+outdoor+furniture+"],"relevanceScore":0.0,"pClick":0.0,"bidPrice":17.0,"rankScore":0.0,"qualityScore":0.0,"costPerClick":0.0,"position":0,"title":"Patio Singer Outdoor Lounge Chair Cover, Waterproof, Outdoor All Weather Protection, Beige Color (Small)","price":14.9,"thumbnail":"https://images-na.ssl-images-amazon.com/images/I/41KzQJGr9WL._AC_US218_.jpg","description":null,"brand":"uFurniture Cover","detail_url":"https://www.amazon.com/dp/B01AP4LWHA","query":"all weather outdoor furniture ","query_group_id":0,"category":"Patio, Lawn & Garden"},{"adId":15,"campaignId":8101,"keyWords":["all+weather+outdoor+furniture+"],"relevanceScore":0.0,"pClick":0.0,"bidPrice":17.0,"rankScore":0.0,"qualityScore":0.0,"costPerClick":0.0,"position":0,"title":"W Unlimited Rustic Collection 2 Piece Patio Chairs Outdoor Furniture Light Brown Rattan Wicker Garden Patio Furniture Bistro Set, Lounger Deep Seating Cushions","price":449.0,"thumbnail":"https://images-na.ssl-images-amazon.com/images/I/41XtNT155kL._AC_US218_.jpg","description":null,"brand":"WUnlimited","detail_url":"https://www.amazon.com/dp/B072HTS9YV","query":"all weather outdoor furniture ","query_group_id":0,"category":"Patio, Lawn & Garden"},{"adId":15,"campaignId":8101,"keyWords":["all+weather+outdoor+furniture+"],"relevanceScore":0.0,"pClick":0.0,"bidPrice":17.0,"rankScore":0.0,"qualityScore":0.0,"costPerClick":0.0,"position":0,"title":"Outdoor Patio Furniture Sofa Modern All Weather Wicker Sectional 7pc Rattan Resin Couch Set","price":1549.0,"thumbnail":"https://images-na.ssl-images-amazon.com/images/I/51JutESWAvL._AC_US218_.jpg","description":null,"brand":"Mango Home","detail_url":"https://www.amazon.com/dp/B00VCJLMCS","query":"all weather outdoor furniture ","query_group_id":0,"category":"Patio, Lawn & Garden"},{"adId":15,"campaignId":8101,"keyWords":["all+weather+outdoor+furniture+"],"relevanceScore":0.0,"pClick":0.0,"bidPrice":17.0,"rankScore":0.0,"qualityScore":0.0,"costPerClick":0.0,"position":0,"title":"Suncrown Outdoor Furniture Sectional Sofa (5-Piece Set) All-Weather Brown Checkered Wicker with Brown Seat Cushions & Modern Glass Coffee Table | Patio, Backyard, Pool | Incl. Waterproof Cover","price":499.95,"thumbnail":"https://images-na.ssl-images-amazon.com/images/I/614IiabsR9L._AC_US218_.jpg","description":null,"brand":"Suncrown","detail_url":"https://www.amazon.com/dp/B06XFF5FVX","query":"all weather outdoor furniture ","query_group_id":0,"category":"Patio, Lawn & Garden"},{"adId":15,"campaignId":8101,"keyWords":["all+weather+outdoor+furniture+"],"relevanceScore":0.0,"pClick":0.0,"bidPrice":17.0,"rankScore":0.0,"qualityScore":0.0,"costPerClick":0.0,"position":0,"title":"Classic Accessories Terrazzo Rectangular/Oval Patio Table Cover - All Weather Protection Outdoor Furniture Cover (58242)","price":25.52,"thumbnail":"https://images-na.ssl-images-amazon.com/images/I/313zPd8-LXL._AC_US218_.jpg","description":null,"brand":"Classic Accessories","detail_url":"https://www.amazon.com/dp/B000MVLB8W","query":"all weather outdoor furniture ","query_group_id":0,"category":"Patio, Lawn & Garden"},{"adId":15,"campaignId":8101,"keyWords":["all+weather+outdoor+furniture+"],"relevanceScore":0.0,"pClick":0.0,"bidPrice":17.0,"rankScore":0.0,"qualityScore":0.0,"costPerClick":0.0,"position":0,"title":"Suncrown Outdoor Furniture Sectional Sofa (4-Piece Set) All-Weather Grey Checkered Wicker with Black Washable Seat Cushions & Glass Coffee Table | Patio, Backyard, Pool | Waterproof Cover & Clips","price":599.95,"thumbnail":"https://images-na.ssl-images-amazon.com/images/I/51jTXO13CRL._AC_US218_.jpg","description":null,"brand":"Suncrown","detail_url":"https://www.amazon.com/dp/B06XFGWRFB","query":"all weather outdoor furniture ","query_group_id":0,"category":"Patio, Lawn & Garden"},{"adId":15,"campaignId":8101,"keyWords":["all+weather+outdoor+furniture+"],"relevanceScore":0.0,"pClick":0.0,"bidPrice":17.0,"rankScore":0.0,"qualityScore":0.0,"costPerClick":0.0,"position":0,"title":"WE Furniture All-Weather Patio Dining Bench, Grey","price":148.73,"thumbnail":"https://images-na.ssl-images-amazon.com/images/I/51FS250L4HL._AC_US218_.jpg","description":null,"brand":"WE Furniture","detail_url":"https://www.amazon.com/dp/B01HOKVR46","query":"all weather outdoor furniture ","query_group_id":0,"category":"Patio, Lawn & Garden"},{"adId":15,"campaignId":8101,"keyWords":["all+weather+outdoor+furniture+"],"relevanceScore":0.0,"pClick":0.0,"bidPrice":17.0,"rankScore":0.0,"qualityScore":0.0,"costPerClick":0.0,"position":0,"title":"Sundale Outdoor 2 Pcs All Weather Patio Furniture Brown Wicker Barstool with Cushions","price":139.99,"thumbnail":"https://images-na.ssl-images-amazon.com/images/I/61eTs0N81UL._AC_US218_.jpg","description":null,"brand":"Sundale Outdoor","detail_url":"https://www.amazon.com/dp/B01L1CZXB6","query":"all weather outdoor furniture ","query_group_id":0,"category":"Patio, Lawn & Garden"},{"adId":15,"campaignId":8101,"keyWords":["all+weather+outdoor+furniture+"],"relevanceScore":0.0,"pClick":0.0,"bidPrice":17.0,"rankScore":0.0,"qualityScore":0.0,"costPerClick":0.0,"position":0,"title":"Outsunny 5 Piece All Weather Rattan Style Wicker Outdoor Patio Dining Set - Brown","price":220.35,"thumbnail":"https://images-na.ssl-images-amazon.com/images/I/41-IYc4hvpL._AC_US218_.jpg","description":null,"brand":"Outsunny","detail_url":"https://www.amazon.com/dp/B0722S8BVC","query":"all weather outdoor furniture ","query_group_id":0,"category":"Patio, Lawn & Garden"},{"adId":15,"campaignId":8101,"keyWords":["all+weather+outdoor+furniture+"],"relevanceScore":0.0,"pClick":0.0,"bidPrice":17.0,"rankScore":0.0,"qualityScore":0.0,"costPerClick":0.0,"position":0,"title":"Cloud Mountain Outdoor 3 Piece Rocking Chair Set Wicker Rattan Bistro Set Wicker Furniture - Two Chairs with Glass Coffee Table, Creamy White Cushion with Cocoa Brown Rattan","price":199.99,"thumbnail":"https://images-na.ssl-images-amazon.com/images/I/41QQ3WfKX0L._AC_US218_.jpg","description":null,"brand":"Cloud Mountain","detail_url":"https://www.amazon.com/dp/B071JL6GTV","query":"all weather outdoor furniture ","query_group_id":0,"category":"Patio, Lawn & Garden"},{"adId":15,"campaignId":8101,"keyWords":["all+weather+outdoor+furniture+"],"relevanceScore":0.0,"pClick":0.0,"bidPrice":17.0,"rankScore":0.0,"qualityScore":0.0,"costPerClick":0.0,"position":0,"title":"Suncast ELEMENTS Loveseat with Storage, Java","price":0.0,"thumbnail":"https://images-na.ssl-images-amazon.com/images/I/51ItmEeN1+L._AC_US218_.jpg","description":null,"brand":"Suncast","detail_url":"https://www.amazon.com/dp/B00UI69BV0","query":"all weather outdoor furniture ","query_group_id":0,"category":"Patio, Lawn & Garden"},{"adId":15,"campaignId":8101,"keyWords":["all+weather+outdoor+furniture+"],"relevanceScore":0.0,"pClick":0.0,"bidPrice":17.0,"rankScore":0.0,"qualityScore":0.0,"costPerClick":0.0,"position":0,"title":"Suncrown Outdoor Furniture High Back Iron Frame Rattan Bench: Wicker Loveseat w/ Cushion - Perfect for Patios, Porches, Gardens or Poolside (White Cushion)","price":69.95,"thumbnail":"https://images-na.ssl-images-amazon.com/images/I/61l7HPlSIUL._AC_US218_.jpg","description":null,"brand":"Suncrown","detail_url":"https://www.amazon.com/dp/B01N159GS1","query":"all weather outdoor furniture ","query_group_id":0,"category":"Patio, Lawn & Garden"},{"adId":15,"campaignId":8101,"keyWords":["all+weather+outdoor+furniture+"],"relevanceScore":0.0,"pClick":0.0,"bidPrice":17.0,"rankScore":0.0,"qualityScore":0.0,"costPerClick":0.0,"position":0,"title":"Urban Furnishing.net - OAHU 7pc Modern Outdoor Backyard Wicker Rattan Patio Furniture Sofa Sectional Couch Set - Charcoal (Gray)","price":1399.0,"thumbnail":"https://images-na.ssl-images-amazon.com/images/I/41SlZEy2BWL._AC_US218_.jpg","description":null,"brand":"UrbanFurnishing.net","detail_url":"https://www.amazon.com/dp/B071R937LN","query":"all weather outdoor furniture ","query_group_id":0,"category":"Patio, Lawn & Garden"},{"adId":15,"campaignId":8101,"keyWords":["all+weather+outdoor+furniture+"],"relevanceScore":0.0,"pClick":0.0,"bidPrice":17.0,"rankScore":0.0,"qualityScore":0.0,"costPerClick":0.0,"position":0,"title":"Classic Accessories Veranda Round Patio Table & Chair Set Cover -  Durable and Water Resistant Outdoor Furniture Cover, Small (71912)","price":35.9,"thumbnail":"https://images-na.ssl-images-amazon.com/images/I/41dFJt3gKrL._AC_US218_.jpg","description":null,"brand":"Classic Accessories","detail_url":"https://www.amazon.com/dp/B000W4AEA0","query":"all weather outdoor furniture ","query_group_id":0,"category":"Patio, Lawn & Garden"},{"adId":15,"campaignId":8101,"keyWords":["all+weather+outdoor+furniture+"],"relevanceScore":0.0,"pClick":0.0,"bidPrice":17.0,"rankScore":0.0,"qualityScore":0.0,"costPerClick":0.0,"position":0,"title":"Suncrown Outdoor Furniture Vibrant Orange Patio Rocking Chair | All-Weather Wicker Seat with Thick, Washable Cushions | Backyard, Pool, Porch | Smooth Gliding Rocker with Improved Stability","price":129.95,"thumbnail":"https://images-na.ssl-images-amazon.com/images/I/617T8z+nPlL._AC_US218_.jpg","description":null,"brand":"Suncrown","detail_url":"https://www.amazon.com/dp/B06XDRP5L1","query":"all weather outdoor furniture ","query_group_id":0,"category":"Patio, Lawn & Garden"},{"adId":15,"campaignId":8101,"keyWords":["all+weather+outdoor+furniture+"],"relevanceScore":0.0,"pClick":0.0,"bidPrice":17.0,"rankScore":0.0,"qualityScore":0.0,"costPerClick":0.0,"position":0,"title":"La-Z-Boy Outdoor Lake Como 5 Piece Resin Wicker Patio Furniture Dining Set (Khaki Tan): Four Dining Chairs and Dining Table, With All Weather Sunsharp Cushions","price":1596.31,"thumbnail":"https://images-na.ssl-images-amazon.com/images/I/41jEjBDL7ZL._AC_US218_.jpg","description":null,"brand":"La-Z-Boy Outdoor","detail_url":"https://www.amazon.com/dp/B007HCBY3Q","query":"all weather outdoor furniture ","query_group_id":0,"category":"Patio, Lawn & Garden"},{"adId":15,"campaignId":8101,"keyWords":["all+weather+outdoor+furniture+"],"relevanceScore":0.0,"pClick":0.0,"bidPrice":17.0,"rankScore":0.0,"qualityScore":0.0,"costPerClick":0.0,"position":0,"title":"Classic Accessories Terrazzo Round Patio Table & Chair Set Cover - All Weather Protection Outdoor Furniture Cover, Medium (58212-EC)","price":36.77,"thumbnail":"https://images-na.ssl-images-amazon.com/images/I/319tptb1wFL._AC_US218_.jpg","description":null,"brand":"Classic Accessories","detail_url":"https://www.amazon.com/dp/B00BD27Y4O","query":"all weather outdoor furniture ","query_group_id":0,"category":"Patio, Lawn & Garden"},{"adId":15,"campaignId":8101,"keyWords":["all+weather+outdoor+furniture+"],"relevanceScore":0.0,"pClick":0.0,"bidPrice":17.0,"rankScore":0.0,"qualityScore":0.0,"costPerClick":0.0,"position":0,"title":"Modern Rattan Outdoor Lounge Chaise - All Weather Patio Chair (Black / Blue)","price":164.99,"thumbnail":"https://images-na.ssl-images-amazon.com/images/I/41UEf4kqosL._AC_US218_.jpg","description":null,"brand":"Divano Roma Furniture","detail_url":"https://www.amazon.com/dp/B01N9XJNF4","query":"all weather outdoor furniture ","query_group_id":0,"category":"Patio, Lawn & Garden"},{"adId":15,"campaignId":8101,"keyWords":["all+weather+outdoor+furniture+"],"relevanceScore":0.0,"pClick":0.0,"bidPrice":17.0,"rankScore":0.0,"qualityScore":0.0,"costPerClick":0.0,"position":0,"title":"Best Choice Products Hanging Chaise Lounger Chair Arc Stand Air Porch Swing Hammock Chair Canopy Red Orange","price":196.52,"thumbnail":"https://images-na.ssl-images-amazon.com/images/I/41eT6GazvdL._AC_US218_.jpg","description":null,"brand":"Best Choice Products","detail_url":"https://www.amazon.com/dp/B00S8USXVM","query":"all weather outdoor furniture ","query_group_id":0,"category":"Patio, Lawn & Garden"},{"adId":15,"campaignId":8101,"keyWords":["all+weather+outdoor+furniture+"],"relevanceScore":0.0,"pClick":0.0,"bidPrice":17.0,"rankScore":0.0,"qualityScore":0.0,"costPerClick":0.0,"position":0,"title":"Abba Patio Outdoor/Porch Rectangular Table and Chair Set Cover, Water proof, All Weather Protection, Tan, 108''L x 82''W x 36''H","price":35.99,"thumbnail":"https://images-na.ssl-images-amazon.com/images/I/41yNOUtzgWL._AC_US218_.jpg","description":null,"brand":"Abba Patio","detail_url":"https://www.amazon.com/dp/B01H38OLCO","query":"all weather outdoor furniture ","query_group_id":0,"category":"Patio, Lawn & Garden"},{"adId":15,"campaignId":8101,"keyWords":["all+weather+outdoor+furniture+"],"relevanceScore":0.0,"pClick":0.0,"bidPrice":17.0,"rankScore":0.0,"qualityScore":0.0,"costPerClick":0.0,"position":0,"title":"Greendale Home Fashions 51-Inch Indoor/Outdoor Bench Cushion, Marine Blue","price":0.0,"thumbnail":"https://images-na.ssl-images-amazon.com/images/I/41ZHhGMnTYL._AC_US218_.jpg","description":null,"brand":"Greendale Home Fashions","detail_url":"https://www.amazon.com/dp/B007CW0QEE","query":"all weather outdoor furniture ","query_group_id":0,"category":"Patio, Lawn & Garden"},{"adId":15,"campaignId":8101,"keyWords":["all+weather+outdoor+furniture+"],"relevanceScore":0.0,"pClick":0.0,"bidPrice":17.0,"rankScore":0.0,"qualityScore":0.0,"costPerClick":0.0,"position":0,"title":"Suncrown Outdoor Furniture Wicker Daybed with Retractable Canopy | Clamshell Seating Separates to 4 Chairs, 1 Table | All-Weather Washable Cushions | Patio, Backyard, Porch, Pool","price":699.95,"thumbnail":"https://images-na.ssl-images-amazon.com/images/I/61oV3f9VGDL._AC_US218_.jpg","description":null,"brand":"Suncrown","detail_url":"https://www.amazon.com/dp/B06XFGKMD7","query":"all weather outdoor furniture ","query_group_id":0,"category":"Patio, Lawn & Garden"},{"adId":15,"campaignId":8101,"keyWords":["all+weather+outdoor+furniture+"],"relevanceScore":0.0,"pClick":0.0,"bidPrice":17.0,"rankScore":0.0,"qualityScore":0.0,"costPerClick":0.0,"position":0,"title":"Best Choice Products Wicker Rocking Chair Patio Porch Deck Furniture All Weather Proof W/ Cushions- Green","price":124.94,"thumbnail":"https://images-na.ssl-images-amazon.com/images/I/518dI1ucA4L._AC_US218_.jpg","description":null,"brand":"Best Choice Products","detail_url":"https://www.amazon.com/dp/B06XXX4TML","query":"all weather outdoor furniture ","query_group_id":0,"category":"Patio, Lawn & Garden"},{"adId":15,"campaignId":8101,"keyWords":["all+weather+outdoor+furniture+"],"relevanceScore":0.0,"pClick":0.0,"bidPrice":17.0,"rankScore":0.0,"qualityScore":0.0,"costPerClick":0.0,"position":0,"title":"Patio Round Table and Chair Set Outdoor Cover, Waterproof, Outdoor All Weather Protection, Beige Color (Large)","price":26.9,"thumbnail":"https://images-na.ssl-images-amazon.com/images/I/41N9Aq0xY1L._AC_US218_.jpg","description":null,"brand":"uFurniture Cover","detail_url":"https://www.amazon.com/dp/B01AOU4NE4","query":"all weather outdoor furniture ","query_group_id":0,"category":"Patio, Lawn & Garden"},{"adId":15,"campaignId":8101,"keyWords":["all+weather+outdoor+furniture+"],"relevanceScore":0.0,"pClick":0.0,"bidPrice":17.0,"rankScore":0.0,"qualityScore":0.0,"costPerClick":0.0,"position":0,"title":"Suncrown Outdoor Furniture Wicker Chairs (2-Piece Set) Thick, Durable Cushions | Partner with Tables, Umbrella Stand or Sofa | Porch, Backyard, Pool or Garden Seating","price":139.95,"thumbnail":"https://images-na.ssl-images-amazon.com/images/I/61DbB64BSIL._AC_US218_.jpg","description":null,"brand":"Suncrown","detail_url":"https://www.amazon.com/dp/B06XD21ZB4","query":"all weather outdoor furniture ","query_group_id":0,"category":"Patio, Lawn & Garden"},{"adId":15,"campaignId":8101,"keyWords":["all+weather+outdoor+furniture+"],"relevanceScore":0.0,"pClick":0.0,"bidPrice":17.0,"rankScore":0.0,"qualityScore":0.0,"costPerClick":0.0,"position":0,"title":"Blazing Needles Tropical/ Stripe All-weather U-shaped Outdoor 3-piece Settee Bench Cushion Set (Tropique Raven REO-30)","price":112.65,"thumbnail":"https://images-na.ssl-images-amazon.com/images/I/51F2FNyf5AL._AC_US218_.jpg","description":null,"brand":"Blazing Needles","detail_url":"https://www.amazon.com/dp/B00YW6QYOO","query":"all weather outdoor furniture ","query_group_id":0,"category":"Patio, Lawn & Garden"},{"adId":15,"campaignId":8101,"keyWords":["all+weather+outdoor+furniture+"],"relevanceScore":0.0,"pClick":0.0,"bidPrice":17.0,"rankScore":0.0,"qualityScore":0.0,"costPerClick":0.0,"position":0,"title":"AE Outdoor 4-Piece Camilla All Weather Wicker Sectional with Sunbrella Fabric","price":2039.99,"thumbnail":"https://images-na.ssl-images-amazon.com/images/I/518x+xTxy5L._AC_US218_.jpg","description":null,"brand":"AE Outdoor","detail_url":"https://www.amazon.com/dp/B00TI813K6","query":"all weather outdoor furniture ","query_group_id":0,"category":"Patio, Lawn & Garden"},{"adId":15,"campaignId":8101,"keyWords":["all+weather+outdoor+furniture+"],"relevanceScore":0.0,"pClick":0.0,"bidPrice":17.0,"rankScore":0.0,"qualityScore":0.0,"costPerClick":0.0,"position":0,"title":"Hanover Outdoor Furniture HVLNA15LI All Weather Contoured Adirondack Chair with Hideaway Ottoman, Lime","price":0.0,"thumbnail":"https://images-na.ssl-images-amazon.com/images/I/415HdJeQ+NL._AC_US218_.jpg","description":null,"brand":"Hanover Outdoor Furniture","detail_url":"https://www.amazon.com/dp/B00VV20AHE","query":"all weather outdoor furniture ","query_group_id":0,"category":"Patio, Lawn & Garden"},{"adId":15,"campaignId":8101,"keyWords":["all+weather+outdoor+furniture+"],"relevanceScore":0.0,"pClick":0.0,"bidPrice":17.0,"rankScore":0.0,"qualityScore":0.0,"costPerClick":0.0,"position":0,"title":"Patio All Weather Outdoor Furniture Set That Seats 4 Comfortably for Enjoying Campfires in the Back Yard or Around the Pool or Deck.","price":585.0,"thumbnail":"https://images-na.ssl-images-amazon.com/images/I/61Irvm7J+BL._AC_US218_.jpg","description":null,"brand":"Azalea Ridge 4-Piece Patio Conversation Set","detail_url":"https://www.amazon.com/dp/B00UZS2EPG","query":"all weather outdoor furniture ","query_group_id":0,"category":"Patio, Lawn & Garden"},{"adId":15,"campaignId":8101,"keyWords":["all+weather+outdoor+furniture+"],"relevanceScore":0.0,"pClick":0.0,"bidPrice":17.0,"rankScore":0.0,"qualityScore":0.0,"costPerClick":0.0,"position":0,"title":"La-Z-Boy Outdoor Sawyer 6 Piece Resin Wicker Patio Furniture Conversation Set (Cilantro Green) With All Weather Sunbrella Cushions","price":0.0,"thumbnail":"https://images-na.ssl-images-amazon.com/images/I/41Y0cze1s5L._AC_US218_.jpg","description":null,"brand":"La-Z-Boy Outdoor","detail_url":"https://www.amazon.com/dp/B00IDDPEB6","query":"all weather outdoor furniture ","query_group_id":0,"category":"Patio, Lawn & Garden"},{"adId":15,"campaignId":8101,"keyWords":["all+weather+outdoor+furniture+"],"relevanceScore":0.0,"pClick":0.0,"bidPrice":17.0,"rankScore":0.0,"qualityScore":0.0,"costPerClick":0.0,"position":0,"title":"Patio Watcher Round Patio Table and Chair Cover All Weather Protective Medium Patio Furniture Cover Furniture Cover 70 Inches(Beige)","price":36.99,"thumbnail":"https://images-na.ssl-images-amazon.com/images/I/311vX++rCAL._AC_US218_.jpg","description":null,"brand":"Patio Watcher","detail_url":"https://www.amazon.com/dp/B06XRV2WLG","query":"all weather outdoor furniture ","query_group_id":0,"category":"Patio, Lawn & Garden"}]