[{"adId":45,"campaignId":8404,"keyWords":["shoe+rack+organizer+"],"relevanceScore":0.0,"pClick":0.0,"bidPrice":7.0,"rankScore":0.0,"qualityScore":0.0,"costPerClick":0.0,"position":0,"title":"Over The Door Shoe Organizer ACMETOP Hanging Shoe Rack with 24 Large Storage Pockets (Beige)","price":17.99,"thumbnail":"https://images-na.ssl-images-amazon.com/images/I/51Htzf7k--L._AC_US218_.jpg","description":null,"brand":"ACMETOP","detail_url":"https://www.amazon.com/dp/B071K5S1LH","query":"shoe rack organizer ","query_group_id":0,"category":"Home & Kitchen"},{"adId":45,"campaignId":8404,"keyWords":["shoe+rack+organizer+"],"relevanceScore":0.0,"pClick":0.0,"bidPrice":7.0,"rankScore":0.0,"qualityScore":0.0,"costPerClick":0.0,"position":0,"title":"OVER THE DOOR SHOE RACK and Closet Organizer System with 24 Exta Large Pockets from Aristocrat Homewares","price":27.99,"thumbnail":"https://images-na.ssl-images-amazon.com/images/I/41guAkHyTEL._AC_US218_.jpg","description":null,"brand":"Aristocrat Homewares","detail_url":"https://www.amazon.com/dp/B00J94627S","query":"shoe rack organizer ","query_group_id":0,"category":"Home & Kitchen"},{"adId":45,"campaignId":8404,"keyWords":["shoe+rack+organizer+"],"relevanceScore":0.0,"pClick":0.0,"bidPrice":7.0,"rankScore":0.0,"qualityScore":0.0,"costPerClick":0.0,"position":0,"title":"","price":0.0,"thumbnail":"","description":null,"brand":"","detail_url":"https://www.amazon.com/dp/B007RP7JU0","query":"shoe rack organizer ","query_group_id":0,"category":"Home & Kitchen"},{"adId":45,"campaignId":8404,"keyWords":["shoe+rack+organizer+"],"relevanceScore":0.0,"pClick":0.0,"bidPrice":7.0,"rankScore":0.0,"qualityScore":0.0,"costPerClick":0.0,"position":0,"title":"Whitmor 20-Pair Floor Shoe Stand, White","price":9.68,"thumbnail":"https://images-na.ssl-images-amazon.com/images/I/51ElmGj1VML._AC_US218_.jpg","description":null,"brand":"Whitmor","detail_url":"https://www.amazon.com/dp/B005KC6DY0","query":"shoe rack organizer ","query_group_id":0,"category":"Home & Kitchen"},{"adId":45,"campaignId":8404,"keyWords":["shoe+rack+organizer+"],"relevanceScore":0.0,"pClick":0.0,"bidPrice":7.0,"rankScore":0.0,"qualityScore":0.0,"costPerClick":0.0,"position":0,"title":"Seville Classics 3-Tier Resin Slat Utility Shoe Rack, Espresso","price":34.0,"thumbnail":"https://images-na.ssl-images-amazon.com/images/I/415PANUlISL._AC_US218_.jpg","description":null,"brand":"Seville Classics","detail_url":"https://www.amazon.com/dp/B00336TY0K","query":"shoe rack organizer ","query_group_id":0,"category":"Home & Kitchen"},{"adId":45,"campaignId":8404,"keyWords":["shoe+rack+organizer+"],"relevanceScore":0.0,"pClick":0.0,"bidPrice":7.0,"rankScore":0.0,"qualityScore":0.0,"costPerClick":0.0,"position":0,"title":"SONGMICS 10 Tiers Shoe Rack with Dustproof Cover Closet Shoe Storage Cabinet Organizer Dark Brown URXJ36Z","price":32.99,"thumbnail":"https://images-na.ssl-images-amazon.com/images/I/41QS2Ju91zL._AC_US218_.jpg","description":null,"brand":"SONGMICS","detail_url":"https://www.amazon.com/dp/B00U5LK20M","query":"shoe rack organizer ","query_group_id":0,"category":"Home & Kitchen"},{"adId":45,"campaignId":8404,"keyWords":["shoe+rack+organizer+"],"relevanceScore":0.0,"pClick":0.0,"bidPrice":7.0,"rankScore":0.0,"qualityScore":0.0,"costPerClick":0.0,"position":0,"title":"Seville Classics 3-Tier Iron Mesh Utility Shoe Rack, Satin Pewter","price":29.88,"thumbnail":"https://images-na.ssl-images-amazon.com/images/I/418FvkbwQoL._AC_US218_.jpg","description":null,"brand":"Seville Classics","detail_url":"https://www.amazon.com/dp/B002QB1DE8","query":"shoe rack organizer ","query_group_id":0,"category":"Home & Kitchen"},{"adId":45,"campaignId":8404,"keyWords":["shoe+rack+organizer+"],"relevanceScore":0.0,"pClick":0.0,"bidPrice":7.0,"rankScore":0.0,"qualityScore":0.0,"costPerClick":0.0,"position":0,"title":"Organize It All Over-The-Door 18-Pair Wire Shoe Rack","price":11.65,"thumbnail":"https://images-na.ssl-images-amazon.com/images/I/41tAIeZrXxL._AC_US218_.jpg","description":null,"brand":"Neu Home","detail_url":"https://www.amazon.com/dp/B002F92P4S","query":"shoe rack organizer ","query_group_id":0,"category":"Home & Kitchen"},{"adId":45,"campaignId":8404,"keyWords":["shoe+rack+organizer+"],"relevanceScore":0.0,"pClick":0.0,"bidPrice":7.0,"rankScore":0.0,"qualityScore":0.0,"costPerClick":0.0,"position":0,"title":"Seville Classics 2-Tier Resin Slat Utility Shoe Rack, Espresso","price":19.29,"thumbnail":"https://images-na.ssl-images-amazon.com/images/I/415GG1mcp4L._AC_US218_.jpg","description":null,"brand":"Seville Classics","detail_url":"https://www.amazon.com/dp/B00FWPQB0G","query":"shoe rack organizer ","query_group_id":0,"category":"Home & Kitchen"},{"adId":45,"campaignId":8404,"keyWords":["shoe+rack+organizer+"],"relevanceScore":0.0,"pClick":0.0,"bidPrice":7.0,"rankScore":0.0,"qualityScore":0.0,"costPerClick":0.0,"position":0,"title":"Grey 10 Tiers Shoe Rack with Dustproof Cover Closet Shoe Storage Cabinet Organizer","price":24.5,"thumbnail":"https://images-na.ssl-images-amazon.com/images/I/41FkmOUv3DL._AC_US218_.jpg","description":null,"brand":"eHomeProducts","detail_url":"https://www.amazon.com/dp/B01M7S23DM","query":"shoe rack organizer ","query_group_id":0,"category":"Home & Kitchen"},{"adId":45,"campaignId":8404,"keyWords":["shoe+rack+organizer+"],"relevanceScore":0.0,"pClick":0.0,"bidPrice":7.0,"rankScore":0.0,"qualityScore":0.0,"costPerClick":0.0,"position":0,"title":"SONGMICS 7 Tiers Portable Shoe Rack Closet with Fabric Cover Shoe Storage Organizer Cabinet Black URXJ12H","price":31.99,"thumbnail":"https://images-na.ssl-images-amazon.com/images/I/41difM5hOlL._AC_US218_.jpg","description":null,"brand":"SONGMICS","detail_url":"https://www.amazon.com/dp/B00XXS14JW","query":"shoe rack organizer ","query_group_id":0,"category":"Home & Kitchen"},{"adId":45,"campaignId":8404,"keyWords":["shoe+rack+organizer+"],"relevanceScore":0.0,"pClick":0.0,"bidPrice":7.0,"rankScore":0.0,"qualityScore":0.0,"costPerClick":0.0,"position":0,"title":"AmazonBasics 50-Pair Shoe Rack","price":34.06,"thumbnail":"https://images-na.ssl-images-amazon.com/images/I/41kwpkNGG2L._AC_US218_.jpg","description":null,"brand":"AmazonBasics","detail_url":"https://www.amazon.com/dp/B00H7P1FHI","query":"shoe rack organizer ","query_group_id":0,"category":"Home & Kitchen"},{"adId":45,"campaignId":8404,"keyWords":["shoe+rack+organizer+"],"relevanceScore":0.0,"pClick":0.0,"bidPrice":7.0,"rankScore":0.0,"qualityScore":0.0,"costPerClick":0.0,"position":0,"title":"Grey 7-Tier Shoe Rack 42-Pair Portable Shoe Storage Cabinet Organizer with Fabric Cover","price":23.95,"thumbnail":"https://images-na.ssl-images-amazon.com/images/I/41YBJ8N3c+L._AC_US218_.jpg","description":null,"brand":"eHomeProducts","detail_url":"https://www.amazon.com/dp/B01M26XZCN","query":"shoe rack organizer ","query_group_id":0,"category":"Home & Kitchen"},{"adId":45,"campaignId":8404,"keyWords":["shoe+rack+organizer+"],"relevanceScore":0.0,"pClick":0.0,"bidPrice":7.0,"rankScore":0.0,"qualityScore":0.0,"costPerClick":0.0,"position":0,"title":"4-Tier Shoe Rack Organizer Storage Bench - Holds 24 Pairs - Organize Your Closet Cabinet or Entryway - Easy to Assemble - No Tools Required","price":27.99,"thumbnail":"https://images-na.ssl-images-amazon.com/images/I/413odqFKcIL._AC_US218_.jpg","description":null,"brand":"Home-Complete","detail_url":"https://www.amazon.com/dp/B013F0RJE6","query":"shoe rack organizer ","query_group_id":0,"category":"Home & Kitchen"},{"adId":45,"campaignId":8404,"keyWords":["shoe+rack+organizer+"],"relevanceScore":0.0,"pClick":0.0,"bidPrice":7.0,"rankScore":0.0,"qualityScore":0.0,"costPerClick":0.0,"position":0,"title":"SONGMICS 4-Tier Shoe Rack Shoe Tower Shelf Storage Organizer Cabinet Grey ULSA14G","price":21.99,"thumbnail":"https://images-na.ssl-images-amazon.com/images/I/51FFos-f97L._AC_US218_.jpg","description":null,"brand":"SONGMICS","detail_url":"https://www.amazon.com/dp/B013LCFM0Q","query":"shoe rack organizer ","query_group_id":0,"category":"Home & Kitchen"},{"adId":45,"campaignId":8404,"keyWords":["shoe+rack+organizer+"],"relevanceScore":0.0,"pClick":0.0,"bidPrice":7.0,"rankScore":0.0,"qualityScore":0.0,"costPerClick":0.0,"position":0,"title":"SONGMICS 10 Tiers Shoe Rack 50 Pairs Non-woven Fabric Shoe Tower Organizer Cabinet Black 39 3/8\" x 11 3/8\" x 68 7/8\" ULSH11H","price":39.99,"thumbnail":"https://images-na.ssl-images-amazon.com/images/I/41n1friMglL._AC_US218_.jpg","description":null,"brand":"SONGMICS","detail_url":"https://www.amazon.com/dp/B00ZOH2J5I","query":"shoe rack organizer ","query_group_id":0,"category":"Home & Kitchen"},{"adId":45,"campaignId":8404,"keyWords":["shoe+rack+organizer+"],"relevanceScore":0.0,"pClick":0.0,"bidPrice":7.0,"rankScore":0.0,"qualityScore":0.0,"costPerClick":0.0,"position":0,"title":"ClosetMaid 8983 Stackable 15-Cube Organizer, White","price":29.97,"thumbnail":"https://images-na.ssl-images-amazon.com/images/I/41szUT7B-ML._AC_US218_.jpg","description":null,"brand":"ClosetMaid","detail_url":"https://www.amazon.com/dp/B002IT6E6A","query":"shoe rack organizer ","query_group_id":0,"category":"Home & Kitchen"},{"adId":45,"campaignId":8404,"keyWords":["shoe+rack+organizer+"],"relevanceScore":0.0,"pClick":0.0,"bidPrice":7.0,"rankScore":0.0,"qualityScore":0.0,"costPerClick":0.0,"position":0,"title":"SONGMICS 10-Tier Shoe Tower Rack with Cover 27-Pair Space Saving Shoe Storage Organizer Grey URXJ10G","price":27.99,"thumbnail":"https://images-na.ssl-images-amazon.com/images/I/41cjac4YvNL._AC_US218_.jpg","description":null,"brand":"SONGMICS","detail_url":"https://www.amazon.com/dp/B00TO5UT6M","query":"shoe rack organizer ","query_group_id":0,"category":"Home & Kitchen"},{"adId":45,"campaignId":8404,"keyWords":["shoe+rack+organizer+"],"relevanceScore":0.0,"pClick":0.0,"bidPrice":7.0,"rankScore":0.0,"qualityScore":0.0,"costPerClick":0.0,"position":0,"title":"SONGMICS 100% Bamboo 4-Tier Shoe Rack Entryway Shoe Shelf Storage Organizer, ULBS94Z","price":35.99,"thumbnail":"https://images-na.ssl-images-amazon.com/images/I/51ON70tni0L._AC_US218_.jpg","description":null,"brand":"SONGMICS","detail_url":"https://www.amazon.com/dp/B01G6IFAZ4","query":"shoe rack organizer ","query_group_id":0,"category":"Home & Kitchen"},{"adId":45,"campaignId":8404,"keyWords":["shoe+rack+organizer+"],"relevanceScore":0.0,"pClick":0.0,"bidPrice":7.0,"rankScore":0.0,"qualityScore":0.0,"costPerClick":0.0,"position":0,"title":"AmazonBasics 3-Shelf Shelving Unit - Black","price":24.67,"thumbnail":"https://images-na.ssl-images-amazon.com/images/I/51qnLO8c+qL._AC_US218_.jpg","description":null,"brand":"AmazonBasics","detail_url":"https://www.amazon.com/dp/B01LWP8AL2","query":"shoe rack organizer ","query_group_id":0,"category":"Home & Kitchen"},{"adId":45,"campaignId":8404,"keyWords":["shoe+rack+organizer+"],"relevanceScore":0.0,"pClick":0.0,"bidPrice":7.0,"rankScore":0.0,"qualityScore":0.0,"costPerClick":0.0,"position":0,"title":"Black / Chocolate Micro Fabric Shoe Rack Storage Organizer & Hallway Bench","price":49.99,"thumbnail":"https://images-na.ssl-images-amazon.com/images/I/51lfa-6Yt6L._AC_US218_.jpg","description":null,"brand":"Ehomeproducts","detail_url":"https://www.amazon.com/dp/B00SLM0GU8","query":"shoe rack organizer ","query_group_id":0,"category":"Home & Kitchen"},{"adId":45,"campaignId":8404,"keyWords":["shoe+rack+organizer+"],"relevanceScore":0.0,"pClick":0.0,"bidPrice":7.0,"rankScore":0.0,"qualityScore":0.0,"costPerClick":0.0,"position":0,"title":"Sodynee 25 Pairs Shoe Rack Shoe Tower Shelf Storage Organizer Stand Cabinet Bench Stackable - Easy to Assemble - No Tools Required, Black","price":23.29,"thumbnail":"https://images-na.ssl-images-amazon.com/images/I/418nP02+vgL._AC_US218_.jpg","description":null,"brand":"Sodynee","detail_url":"https://www.amazon.com/dp/B01HYY5CI4","query":"shoe rack organizer ","query_group_id":0,"category":"Home & Kitchen"},{"adId":45,"campaignId":8404,"keyWords":["shoe+rack+organizer+"],"relevanceScore":0.0,"pClick":0.0,"bidPrice":7.0,"rankScore":0.0,"qualityScore":0.0,"costPerClick":0.0,"position":0,"title":"SONGMICS 5 Tiers Shoe Rack Space Saving Shoe Tower Cabinet Storage Organizer Black 39\"L Holds 20-25 Pair of Shoes ULSH55H","price":27.99,"thumbnail":"https://images-na.ssl-images-amazon.com/images/I/51X26Ob5GSL._AC_US218_.jpg","description":null,"brand":"SONGMICS","detail_url":"https://www.amazon.com/dp/B00ZOEMT1K","query":"shoe rack organizer ","query_group_id":0,"category":"Home & Kitchen"},{"adId":45,"campaignId":8404,"keyWords":["shoe+rack+organizer+"],"relevanceScore":0.0,"pClick":0.0,"bidPrice":7.0,"rankScore":0.0,"qualityScore":0.0,"costPerClick":0.0,"position":0,"title":"Honey-Can-Do SHO-01599 Bamboo 3-Tier Shoe Shelf","price":23.99,"thumbnail":"https://images-na.ssl-images-amazon.com/images/I/51MqqrpMz0L._AC_US218_.jpg","description":null,"brand":"Honey-Can-Do","detail_url":"https://www.amazon.com/dp/B00302KB40","query":"shoe rack organizer ","query_group_id":0,"category":"Home & Kitchen"},{"adId":45,"campaignId":8404,"keyWords":["shoe+rack+organizer+"],"relevanceScore":0.0,"pClick":0.0,"bidPrice":7.0,"rankScore":0.0,"qualityScore":0.0,"costPerClick":0.0,"position":0,"title":"SONGMICS DIY Shoe Rack 12-cube Shoe Cabinet Plastic Shoe Storage Organizer with Doors Black ULPC26H","price":54.99,"thumbnail":"https://images-na.ssl-images-amazon.com/images/I/51pNeL9AL9L._AC_US218_.jpg","description":null,"brand":"SONGMICS","detail_url":"https://www.amazon.com/dp/B01LH2VJWM","query":"shoe rack organizer ","query_group_id":0,"category":"Home & Kitchen"},{"adId":45,"campaignId":8404,"keyWords":["shoe+rack+organizer+"],"relevanceScore":0.0,"pClick":0.0,"bidPrice":7.0,"rankScore":0.0,"qualityScore":0.0,"costPerClick":0.0,"position":0,"title":"Whitmor OTD Shoe Bag, 24 Pocket White Crystal","price":9.99,"thumbnail":"https://images-na.ssl-images-amazon.com/images/I/41X-n9-5TRL._AC_US218_.jpg","description":null,"brand":"Whitmor","detail_url":"https://www.amazon.com/dp/B000HM5V0A","query":"shoe rack organizer ","query_group_id":0,"category":"Home & Kitchen"},{"adId":45,"campaignId":8404,"keyWords":["shoe+rack+organizer+"],"relevanceScore":0.0,"pClick":0.0,"bidPrice":7.0,"rankScore":0.0,"qualityScore":0.0,"costPerClick":0.0,"position":0,"title":"Shoes Away Shoes Away Hanging Shoe Organizer","price":14.14,"thumbnail":"https://images-na.ssl-images-amazon.com/images/I/418J2Sp8zrL._AC_US218_.jpg","description":null,"brand":"Shoes Away!","detail_url":"https://www.amazon.com/dp/B000HJGBYI","query":"shoe rack organizer ","query_group_id":0,"category":"Home & Kitchen"},{"adId":45,"campaignId":8404,"keyWords":["shoe+rack+organizer+"],"relevanceScore":0.0,"pClick":0.0,"bidPrice":7.0,"rankScore":0.0,"qualityScore":0.0,"costPerClick":0.0,"position":0,"title":"Wood Shoe Rack, Storage Bench – Closet, Bathroom, Kitchen, Entry Organizer, 3-Tier Space Saver Shoe Rack by Lavish Home","price":15.35,"thumbnail":"https://images-na.ssl-images-amazon.com/images/I/51zShO2n0YL._AC_US218_.jpg","description":null,"brand":"Lavish Home","detail_url":"https://www.amazon.com/dp/B00MRYMQCW","query":"shoe rack organizer ","query_group_id":0,"category":"Home & Kitchen"},{"adId":45,"campaignId":8404,"keyWords":["shoe+rack+organizer+"],"relevanceScore":0.0,"pClick":0.0,"bidPrice":7.0,"rankScore":0.0,"qualityScore":0.0,"costPerClick":0.0,"position":0,"title":"SONGMICS 3-Tier Stackable Metal Shoe Rack Flat & Slant Adjustable Shoe Organizer Shelf for Closet Bedroom & Entryway Bronze ULMR03A","price":35.99,"thumbnail":"https://images-na.ssl-images-amazon.com/images/I/51bkBMsNzwL._AC_US218_.jpg","description":null,"brand":"SONGMICS","detail_url":"https://www.amazon.com/dp/B01J3JA3Y6","query":"shoe rack organizer ","query_group_id":0,"category":"Home & Kitchen"},{"adId":45,"campaignId":8404,"keyWords":["shoe+rack+organizer+"],"relevanceScore":0.0,"pClick":0.0,"bidPrice":7.0,"rankScore":0.0,"qualityScore":0.0,"costPerClick":0.0,"position":0,"title":"Furinno Pine Solid Wood 4-Tier Shoe Rack, Espresso","price":17.5,"thumbnail":"https://images-na.ssl-images-amazon.com/images/I/41x9ZbXAh2L._AC_US218_.jpg","description":null,"brand":"Furinno","detail_url":"https://www.amazon.com/dp/B00KNBRV6C","query":"shoe rack organizer ","query_group_id":0,"category":"Home & Kitchen"},{"adId":45,"campaignId":8404,"keyWords":["shoe+rack+organizer+"],"relevanceScore":0.0,"pClick":0.0,"bidPrice":7.0,"rankScore":0.0,"qualityScore":0.0,"costPerClick":0.0,"position":0,"title":"OxGord 50-Pair Shoe Rack Storage Organizer, 10-Tier Portable Wardrobe Closet Bench Tower Stackable, Adjustable Shelf - Strong & Sturdy Space Saver Wont Weaken or Collapse - Black","price":18.95,"thumbnail":"https://images-na.ssl-images-amazon.com/images/I/51cP9v0QgwL._AC_US218_.jpg","description":null,"brand":"OxGord","detail_url":"https://www.amazon.com/dp/B00XO3DVOM","query":"shoe rack organizer ","query_group_id":0,"category":"Home & Kitchen"},{"adId":45,"campaignId":8404,"keyWords":["shoe+rack+organizer+"],"relevanceScore":0.0,"pClick":0.0,"bidPrice":7.0,"rankScore":0.0,"qualityScore":0.0,"costPerClick":0.0,"position":0,"title":"SONGMICS 3-Tier Shoe Rack Shoe Tower Shelf Storage Organizer Cabinet Grey ULSA13G","price":21.99,"thumbnail":"https://images-na.ssl-images-amazon.com/images/I/51N7Hb9My0L._AC_US218_.jpg","description":null,"brand":"SONGMICS","detail_url":"https://www.amazon.com/dp/B01IEILN8M","query":"shoe rack organizer ","query_group_id":0,"category":"Home & Kitchen"},{"adId":45,"campaignId":8404,"keyWords":["shoe+rack+organizer+"],"relevanceScore":0.0,"pClick":0.0,"bidPrice":7.0,"rankScore":0.0,"qualityScore":0.0,"costPerClick":0.0,"position":0,"title":"Whitmor 36-Pair OTD Shoe Rack, White","price":12.61,"thumbnail":"https://images-na.ssl-images-amazon.com/images/I/41ExYFpGw2L._AC_US218_.jpg","description":null,"brand":"Whitmor","detail_url":"https://www.amazon.com/dp/B00HFJODD4","query":"shoe rack organizer ","query_group_id":0,"category":"Home & Kitchen"},{"adId":45,"campaignId":8404,"keyWords":["shoe+rack+organizer+"],"relevanceScore":0.0,"pClick":0.0,"bidPrice":7.0,"rankScore":0.0,"qualityScore":0.0,"costPerClick":0.0,"position":0,"title":"FCH 10 Tier 50 Pair Shoes Storage Organizer Rack for Space Saving Shoes Closet Organizer","price":20.58,"thumbnail":"https://images-na.ssl-images-amazon.com/images/I/51Qn-nuDAzL._AC_US218_.jpg","description":null,"brand":"FCH","detail_url":"https://www.amazon.com/dp/B01M3XJXAI","query":"shoe rack organizer ","query_group_id":0,"category":"Home & Kitchen"},{"adId":45,"campaignId":8404,"keyWords":["shoe+rack+organizer+"],"relevanceScore":0.0,"pClick":0.0,"bidPrice":7.0,"rankScore":0.0,"qualityScore":0.0,"costPerClick":0.0,"position":0,"title":"Wall Mounted Shoes Rack - 4 PCS Plastic Shoe Storage Racks for Entryway Over the Door Shoe Hangers Organizer Hanging","price":10.99,"thumbnail":"https://images-na.ssl-images-amazon.com/images/I/51JHQls6zwL._AC_US218_.jpg","description":null,"brand":"FineFineBest","detail_url":"https://www.amazon.com/dp/B06XVR7FPZ","query":"shoe rack organizer ","query_group_id":0,"category":"Home & Kitchen"},{"adId":45,"campaignId":8404,"keyWords":["shoe+rack+organizer+"],"relevanceScore":0.0,"pClick":0.0,"bidPrice":7.0,"rankScore":0.0,"qualityScore":0.0,"costPerClick":0.0,"position":0,"title":"StorageManiac Free Standing Polyester Canvas 5-Tier, 20-Pair Shoe Rack Organizer","price":42.39,"thumbnail":"https://images-na.ssl-images-amazon.com/images/I/41nc7pxWJCL._AC_US218_.jpg","description":null,"brand":"Storagemaniac","detail_url":"https://www.amazon.com/dp/B00FZH1Z5M","query":"shoe rack organizer ","query_group_id":0,"category":"Home & Kitchen"},{"adId":45,"campaignId":8404,"keyWords":["shoe+rack+organizer+"],"relevanceScore":0.0,"pClick":0.0,"bidPrice":7.0,"rankScore":0.0,"qualityScore":0.0,"costPerClick":0.0,"position":0,"title":"Whitmor 36-Pair OTD Shoe Rack, White","price":0.0,"thumbnail":"https://images-na.ssl-images-amazon.com/images/I/41eOUCW3r5L._AC_US218_.jpg","description":null,"brand":"Whitmor","detail_url":"https://www.amazon.com/dp/B0019FOUQ0","query":"shoe rack organizer ","query_group_id":0,"category":"Home & Kitchen"},{"adId":45,"campaignId":8404,"keyWords":["shoe+rack+organizer+"],"relevanceScore":0.0,"pClick":0.0,"bidPrice":7.0,"rankScore":0.0,"qualityScore":0.0,"costPerClick":0.0,"position":0,"title":"Richards Homewares Hanging Ten Shoe Large Shelf Organizer-Canvas/Natural 50\" x 14\" x 8\"","price":19.38,"thumbnail":"https://images-na.ssl-images-amazon.com/images/I/31AmffNX5TL._AC_US218_.jpg","description":null,"brand":"Richards Homewares","detail_url":"https://www.amazon.com/dp/B0000TQEZ6","query":"shoe rack organizer ","query_group_id":0,"category":"Home & Kitchen"},{"adId":45,"campaignId":8404,"keyWords":["shoe+rack+organizer+"],"relevanceScore":0.0,"pClick":0.0,"bidPrice":7.0,"rankScore":0.0,"qualityScore":0.0,"costPerClick":0.0,"position":0,"title":"SONGMICS 2-tier Shoe Bench Organizing Rack Entryway Storage Shelf 100% Bamboo ULBS04N","price":32.99,"thumbnail":"https://images-na.ssl-images-amazon.com/images/I/51iunx8TJGL._AC_US218_.jpg","description":null,"brand":"SONGMICS","detail_url":"https://www.amazon.com/dp/B00NL8NB6S","query":"shoe rack organizer ","query_group_id":0,"category":"Home & Kitchen"},{"adId":45,"campaignId":8404,"keyWords":["shoe+rack+organizer+"],"relevanceScore":0.0,"pClick":0.0,"bidPrice":7.0,"rankScore":0.0,"qualityScore":0.0,"costPerClick":0.0,"position":0,"title":"50 Pair 10 Tier Space Saving Storage Organizer Free Standing Shoe Tower Rack","price":20.73,"thumbnail":"https://images-na.ssl-images-amazon.com/images/I/51Q9dHD6PJL._AC_US218_.jpg","description":null,"brand":"Home & Garden","detail_url":"https://www.amazon.com/dp/B01LW3OGA5","query":"shoe rack organizer ","query_group_id":0,"category":"Home & Kitchen"},{"adId":45,"campaignId":8404,"keyWords":["shoe+rack+organizer+"],"relevanceScore":0.0,"pClick":0.0,"bidPrice":7.0,"rankScore":0.0,"qualityScore":0.0,"costPerClick":0.0,"position":0,"title":"24 Pockets - OVER THE DOOR SHOE RACK and Closet Organizer System for Maximizing Storage,4 Customized Over the Door Hooks","price":20.99,"thumbnail":"https://images-na.ssl-images-amazon.com/images/I/414V8xcUgsL._AC_US218_.jpg","description":null,"brand":"COMFITS","detail_url":"https://www.amazon.com/dp/B01N48JN4A","query":"shoe rack organizer ","query_group_id":0,"category":"Home & Kitchen"},{"adId":45,"campaignId":8404,"keyWords":["shoe+rack+organizer+"],"relevanceScore":0.0,"pClick":0.0,"bidPrice":7.0,"rankScore":0.0,"qualityScore":0.0,"costPerClick":0.0,"position":0,"title":"Suncast GO3216 Golf Organizer","price":68.89,"thumbnail":"https://images-na.ssl-images-amazon.com/images/I/515msBNxuUL._AC_US218_.jpg","description":null,"brand":"Suncast","detail_url":"https://www.amazon.com/dp/B0000V0L9Y","query":"shoe rack organizer ","query_group_id":0,"category":"Home & Kitchen"},{"adId":45,"campaignId":8404,"keyWords":["shoe+rack+organizer+"],"relevanceScore":0.0,"pClick":0.0,"bidPrice":7.0,"rankScore":0.0,"qualityScore":0.0,"costPerClick":0.0,"position":0,"title":"Closet Shoe Organizer Storage Cabinet Cube, 25 Pair Floor Cubby - Espresso","price":69.99,"thumbnail":"https://images-na.ssl-images-amazon.com/images/I/41mC8+fjvqL._AC_US218_.jpg","description":null,"brand":"xt","detail_url":"https://www.amazon.com/dp/B00LFW3JVO","query":"shoe rack organizer ","query_group_id":0,"category":"Home & Kitchen"},{"adId":45,"campaignId":8404,"keyWords":["shoe+rack+organizer+"],"relevanceScore":0.0,"pClick":0.0,"bidPrice":7.0,"rankScore":0.0,"qualityScore":0.0,"costPerClick":0.0,"position":0,"title":"Homdox Portable Shoe Storage Cabinet Space Saving Shoe Tower Rack Organizer","price":23.59,"thumbnail":"https://images-na.ssl-images-amazon.com/images/I/51z3xZY8q+L._AC_US218_.jpg","description":null,"brand":"Homdox","detail_url":"https://www.amazon.com/dp/B019YVVEM8","query":"shoe rack organizer ","query_group_id":0,"category":"Home & Kitchen"},{"adId":45,"campaignId":8404,"keyWords":["shoe+rack+organizer+"],"relevanceScore":0.0,"pClick":0.0,"bidPrice":7.0,"rankScore":0.0,"qualityScore":0.0,"costPerClick":0.0,"position":0,"title":"SONGMICS Entryway Bamboo Shoe Bench 2-Tier Shoe Rack Organizer Brown ULBS04Z","price":35.99,"thumbnail":"https://images-na.ssl-images-amazon.com/images/I/51r5Khr59mL._AC_US218_.jpg","description":null,"brand":"SONGMICS","detail_url":"https://www.amazon.com/dp/B01MR781H2","query":"shoe rack organizer ","query_group_id":0,"category":"Home & Kitchen"},{"adId":45,"campaignId":8404,"keyWords":["shoe+rack+organizer+"],"relevanceScore":0.0,"pClick":0.0,"bidPrice":7.0,"rankScore":0.0,"qualityScore":0.0,"costPerClick":0.0,"position":0,"title":"Father's Day Horseshoe Boot Rack - 2 Pairs, 3 Pairs, and 4 Pairs - The Heritage Forge - Boot Holder","price":79.99,"thumbnail":"https://images-na.ssl-images-amazon.com/images/I/41qfyjeK43L._AC_US218_.jpg","description":null,"brand":"The Heritage Forge","detail_url":"https://www.amazon.com/dp/B06XCPWDC7","query":"shoe rack organizer ","query_group_id":0,"category":"Home & Kitchen"},{"adId":45,"campaignId":8404,"keyWords":["shoe+rack+organizer+"],"relevanceScore":0.0,"pClick":0.0,"bidPrice":7.0,"rankScore":0.0,"qualityScore":0.0,"costPerClick":0.0,"position":0,"title":"Happu-store(TM) 1PC Shoes Organizer Display Rack Space-Saving Storage Rack Plastic","price":4.57,"thumbnail":"https://images-na.ssl-images-amazon.com/images/I/41wdBe400cL._AC_US218_.jpg","description":"... Our space-optimizing shoe organizer will help you double your shoe ...","brand":"happu-store","detail_url":"https://www.amazon.com/dp/B01J7H5S4E","query":"shoe rack organizer ","query_group_id":0,"category":"Home & Kitchen"},{"adId":45,"campaignId":8404,"keyWords":["shoe+rack+organizer+"],"relevanceScore":0.0,"pClick":0.0,"bidPrice":7.0,"rankScore":0.0,"qualityScore":0.0,"costPerClick":0.0,"position":0,"title":"Wooden Shoe Rack Organizer Storage Shelf 3 Tier Closet Compact Cabinet H28","price":0.0,"thumbnail":"https://images-na.ssl-images-amazon.com/images/I/41JNu+G5ueL._AC_US218_.jpg","description":"High Quality Wooden stackable 3 step shoe rack","brand":"BWUK","detail_url":"https://www.amazon.com/dp/B01JP38R84","query":"shoe rack organizer ","query_group_id":0,"category":"Home & Kitchen"},{"adId":45,"campaignId":8404,"keyWords":["shoe+rack+organizer+"],"relevanceScore":0.0,"pClick":0.0,"bidPrice":7.0,"rankScore":0.0,"qualityScore":0.0,"costPerClick":0.0,"position":0,"title":"SmartHome 10 Tiers Shoe Rack 50 Pairs Non-woven Fabric Shoe Tower Storage Organizer Cabinet Grey","price":24.99,"thumbnail":"https://images-na.ssl-images-amazon.com/images/I/41CB9Ic4LLL._AC_US218_.jpg","description":null,"brand":"Smart home","detail_url":"https://www.amazon.com/dp/B01HC8V49S","query":"shoe rack organizer ","query_group_id":0,"category":"Home & Kitchen"}]